{
  "Id": 50,
  "AudioSource": "050_Dareso",
  "Name": "誰ソ彼アイデンティティー",
  "Difficulty": 4,
  "Notes": [
    { "Index": 0, "TimeValue": 20.0000, "Time": "00:20.0000", "Line": 9, "Width": 3, "Type": 145 },
    { "Index": 1, "TimeValue": 72.1153, "Time": "01:12.1153", "Line": 6, "Width": 3, "Type": 145 },
    { "Index": 2, "TimeValue": 102.1153, "Time": "01:42.1153", "Line": 6, "Width": 6, "Type": 17 },
    { "Index": 3, "TimeValue": 102.6923, "Time": "01:42.6923", "Line": 0, "Width": 6, "Type": 17 },
    { "Index": 4, "TimeValue": 101.5384, "Time": "01:41.5384", "Line": 0, "Width": 6, "Type": 97 },
    { "Index": 5, "TimeValue": 56.9230, "Time": "00:56.9230", "Line": 9, "Width": 3, "Type": 97 },
    { "Index": 6, "TimeValue": 25.3846, "Time": "00:25.3846", "Line": 0, "Width": 3, "Type": 97 },
    { "Index": 7, "TimeValue": 23.8461, "Time": "00:23.8461", "Line": 6, "Width": 3, "Type": 49 },
    { "Index": 8, "TimeValue": 24.4230, "Time": "00:24.4230", "Line": 6, "Width": 3, "Type": 83 },
    { "Index": 9, "TimeValue": 41.5384, "Time": "00:41.5384", "Line": 9, "Width": 3, "Type": 49 },
    { "Index": 10, "TimeValue": 42.3076, "Time": "00:42.3076", "Line": 6, "Width": 3, "Type": 83 },
    { "Index": 11, "TimeValue": 66.9230, "Time": "01:06.9230", "Line": 6, "Width": 4, "Type": 41 },
    { "Index": 12, "TimeValue": 73.8461, "Time": "01:13.8461", "Line": 3, "Width": 3, "Type": 49 },
    { "Index": 13, "TimeValue": 74.4230, "Time": "01:14.4230", "Line": 0, "Width": 3, "Type": 83 },
    { "Index": 14, "TimeValue": 83.6538, "Time": "01:23.6538", "Line": 0, "Width": 6, "Type": 37 },
    { "Index": 15, "TimeValue": 120.7692, "Time": "02:00.7692", "Line": 0, "Width": 3, "Type": 49 },
    { "Index": 16, "TimeValue": 121.1538, "Time": "02:01.1538", "Line": 3, "Width": 3, "Type": 83 },
    { "Index": 17, "TimeValue": 122.3076, "Time": "02:02.3076", "Line": 3, "Width": 3, "Type": 49 },
    { "Index": 18, "TimeValue": 126.5384, "Time": "02:06.5384", "Line": 3, "Width": 3, "Type": 83 },
    { "Index": 19, "TimeValue": 4.1346, "Time": "00:04.1346", "Line": 0, "Width": 3, "Type": 17 },
    { "Index": 20, "TimeValue": 4.3269, "Time": "00:04.3269", "Line": 3, "Width": 3, "Type": 17 },
    { "Index": 21, "TimeValue": 6.5384, "Time": "00:06.5384", "Line": 0, "Width": 3, "Type": 17 },
    { "Index": 22, "TimeValue": 6.7307, "Time": "00:06.7307", "Line": 6, "Width": 3, "Type": 17 },
    { "Index": 23, "TimeValue": 8.0769, "Time": "00:08.0769", "Line": 0, "Width": 3, "Type": 17 },
    { "Index": 24, "TimeValue": 10.4807, "Time": "00:10.4807", "Line": 6, "Width": 3, "Type": 17 },
    { "Index": 25, "TimeValue": 10.3846, "Time": "00:10.3846", "Line": 0, "Width": 3, "Type": 17 },
    { "Index": 26, "TimeValue": 10.5769, "Time": "00:10.5769", "Line": 3, "Width": 3, "Type": 17 },
    { "Index": 27, "TimeValue": 10.6730, "Time": "00:10.6730", "Line": 9, "Width": 3, "Type": 17 },
    { "Index": 28, "TimeValue": 14.0384, "Time": "00:14.0384", "Line": 6, "Width": 3, "Type": 17 },
    { "Index": 29, "TimeValue": 14.8076, "Time": "00:14.8076", "Line": 6, "Width": 3, "Type": 17 },
    { "Index": 30, "TimeValue": 20.1923, "Time": "00:20.1923", "Line": 6, "Width": 3, "Type": 17 },
    { "Index": 31, "TimeValue": 20.3846, "Time": "00:20.3846", "Line": 3, "Width": 3, "Type": 17 },
    { "Index": 32, "TimeValue": 20.5769, "Time": "00:20.5769", "Line": 9, "Width": 3, "Type": 17 },
    { "Index": 33, "TimeValue": 20.7692, "Time": "00:20.7692", "Line": 0, "Width": 3, "Type": 17 },
    { "Index": 34, "TimeValue": 20.9615, "Time": "00:20.9615", "Line": 6, "Width": 3, "Type": 17 },
    { "Index": 35, "TimeValue": 25.5769, "Time": "00:25.5769", "Line": 6, "Width": 3, "Type": 17 },
    { "Index": 36, "TimeValue": 25.7692, "Time": "00:25.7692", "Line": 3, "Width": 3, "Type": 17 },
    { "Index": 37, "TimeValue": 26.5384, "Time": "00:26.5384", "Line": 6, "Width": 3, "Type": 17 },
    { "Index": 38, "TimeValue": 27.5000, "Time": "00:27.5000", "Line": 6, "Width": 3, "Type": 17 },
    { "Index": 39, "TimeValue": 28.2692, "Time": "00:28.2692", "Line": 0, "Width": 3, "Type": 17 },
    { "Index": 40, "TimeValue": 28.4615, "Time": "00:28.4615", "Line": 0, "Width": 3, "Type": 17 },
    { "Index": 41, "TimeValue": 29.2307, "Time": "00:29.2307", "Line": 6, "Width": 3, "Type": 17 },
    { "Index": 42, "TimeValue": 29.6153, "Time": "00:29.6153", "Line": 3, "Width": 3, "Type": 17 },
    { "Index": 43, "TimeValue": 31.9230, "Time": "00:31.9230", "Line": 6, "Width": 3, "Type": 17 },
    { "Index": 44, "TimeValue": 40.7692, "Time": "00:40.7692", "Line": 3, "Width": 3, "Type": 17 },
    { "Index": 45, "TimeValue": 41.1538, "Time": "00:41.1538", "Line": 6, "Width": 3, "Type": 17 },
    { "Index": 46, "TimeValue": 56.7307, "Time": "00:56.7307", "Line": 6, "Width": 3, "Type": 17 },
    { "Index": 47, "TimeValue": 61.9230, "Time": "01:01.9230", "Line": 9, "Width": 3, "Type": 17 },
    { "Index": 48, "TimeValue": 62.1153, "Time": "01:02.1153", "Line": 3, "Width": 3, "Type": 17 },
    { "Index": 49, "TimeValue": 62.5000, "Time": "01:02.5000", "Line": 6, "Width": 3, "Type": 17 },
    { "Index": 50, "TimeValue": 60.3846, "Time": "01:00.3846", "Line": 3, "Width": 3, "Type": 17 },
    { "Index": 51, "TimeValue": 62.6923, "Time": "01:02.6923", "Line": 3, "Width": 3, "Type": 17 },
    { "Index": 52, "TimeValue": 63.6538, "Time": "01:03.6538", "Line": 3, "Width": 3, "Type": 17 },
    { "Index": 53, "TimeValue": 68.6538, "Time": "01:08.6538", "Line": 0, "Width": 3, "Type": 17 },
    { "Index": 54, "TimeValue": 68.8461, "Time": "01:08.8461", "Line": 3, "Width": 3, "Type": 17 },
    { "Index": 55, "TimeValue": 69.0384, "Time": "01:09.0384", "Line": 6, "Width": 3, "Type": 17 },
    { "Index": 56, "TimeValue": 69.4230, "Time": "01:09.4230", "Line": 3, "Width": 3, "Type": 17 },
    { "Index": 57, "TimeValue": 74.2307, "Time": "01:14.2307", "Line": 6, "Width": 3, "Type": 17 },
    { "Index": 58, "TimeValue": 74.8076, "Time": "01:14.8076", "Line": 6, "Width": 3, "Type": 17 },
    { "Index": 59, "TimeValue": 75.0000, "Time": "01:15.0000", "Line": 3, "Width": 3, "Type": 17 },
    { "Index": 60, "TimeValue": 75.1923, "Time": "01:15.1923", "Line": 0, "Width": 3, "Type": 17 },
    { "Index": 61, "TimeValue": 81.7307, "Time": "01:21.7307", "Line": 6, "Width": 3, "Type": 17 },
    { "Index": 62, "TimeValue": 81.9230, "Time": "01:21.9230", "Line": 3, "Width": 3, "Type": 17 },
    { "Index": 63, "TimeValue": 82.3076, "Time": "01:22.3076", "Line": 3, "Width": 6, "Type": 17 },
    { "Index": 64, "TimeValue": 92.1153, "Time": "01:32.1153", "Line": 6, "Width": 3, "Type": 17 },
    { "Index": 65, "TimeValue": 95.5769, "Time": "01:35.5769", "Line": 3, "Width": 3, "Type": 17 },
    { "Index": 66, "TimeValue": 95.7692, "Time": "01:35.7692", "Line": 6, "Width": 3, "Type": 17 },
    { "Index": 67, "TimeValue": 95.9615, "Time": "01:35.9615", "Line": 0, "Width": 3, "Type": 17 },
    { "Index": 68, "TimeValue": 97.3076, "Time": "01:37.3076", "Line": 0, "Width": 3, "Type": 17 },
    { "Index": 69, "TimeValue": 97.5000, "Time": "01:37.5000", "Line": 6, "Width": 3, "Type": 17 },
    { "Index": 70, "TimeValue": 105.7692, "Time": "01:45.7692", "Line": 0, "Width": 3, "Type": 17 },
    { "Index": 71, "TimeValue": 105.8653, "Time": "01:45.8653", "Line": 6, "Width": 3, "Type": 17 },
    { "Index": 72, "TimeValue": 105.9615, "Time": "01:45.9615", "Line": 3, "Width": 3, "Type": 17 },
    { "Index": 73, "TimeValue": 106.0576, "Time": "01:46.0576", "Line": 9, "Width": 3, "Type": 17 },
    { "Index": 74, "TimeValue": 106.3461, "Time": "01:46.3461", "Line": 9, "Width": 3, "Type": 17 },
    { "Index": 75, "TimeValue": 117.8846, "Time": "01:57.8846", "Line": 6, "Width": 3, "Type": 17 },
    { "Index": 76, "TimeValue": 118.0769, "Time": "01:58.0769", "Line": 3, "Width": 3, "Type": 17 },
    { "Index": 77, "TimeValue": 121.9230, "Time": "02:01.9230", "Line": 3, "Width": 6, "Type": 17 },
    { "Index": 78, "TimeValue": 4.2307, "Time": "00:04.2307", "Line": 6, "Width": 3, "Type": 17 },
    { "Index": 79, "TimeValue": 4.6153, "Time": "00:04.6153", "Line": 9, "Width": 3, "Type": 145 },
    { "Index": 80, "TimeValue": 4.8076, "Time": "00:04.8076", "Line": 3, "Width": 3, "Type": 17 },
    { "Index": 81, "TimeValue": 5.0000, "Time": "00:05.0000", "Line": 6, "Width": 3, "Type": 17 },
    { "Index": 82, "TimeValue": 5.1923, "Time": "00:05.1923", "Line": 0, "Width": 3, "Type": 17 },
    { "Index": 83, "TimeValue": 5.3846, "Time": "00:05.3846", "Line": 9, "Width": 3, "Type": 17 },
    { "Index": 84, "TimeValue": 5.5769, "Time": "00:05.5769", "Line": 3, "Width": 3, "Type": 49 },
    { "Index": 85, "TimeValue": 5.9615, "Time": "00:05.9615", "Line": 3, "Width": 3, "Type": 83 },
    { "Index": 86, "TimeValue": 5.9615, "Time": "00:05.9615", "Line": 9, "Width": 3, "Type": 41 },
    { "Index": 87, "TimeValue": 6.9230, "Time": "00:06.9230", "Line": 3, "Width": 3, "Type": 17 },
    { "Index": 88, "TimeValue": 7.1153, "Time": "00:07.1153", "Line": 9, "Width": 3, "Type": 49 },
    { "Index": 89, "TimeValue": 7.5000, "Time": "00:07.5000", "Line": 9, "Width": 3, "Type": 83 },
    { "Index": 90, "TimeValue": 7.5000, "Time": "00:07.5000", "Line": 0, "Width": 3, "Type": 37 },
    { "Index": 91, "TimeValue": 8.2692, "Time": "00:08.2692", "Line": 6, "Width": 3, "Type": 17 },
    { "Index": 92, "TimeValue": 8.4615, "Time": "00:08.4615", "Line": 3, "Width": 3, "Type": 17 },
    { "Index": 93, "TimeValue": 8.6538, "Time": "00:08.6538", "Line": 9, "Width": 3, "Type": 17 },
    { "Index": 94, "TimeValue": 9.0384, "Time": "00:09.0384", "Line": 3, "Width": 3, "Type": 17 },
    { "Index": 95, "TimeValue": 9.2307, "Time": "00:09.2307", "Line": 0, "Width": 3, "Type": 17 },
    { "Index": 96, "TimeValue": 9.2307, "Time": "00:09.2307", "Line": 6, "Width": 3, "Type": 17 },
    { "Index": 97, "TimeValue": 9.4230, "Time": "00:09.4230", "Line": 3, "Width": 3, "Type": 49 },
    { "Index": 98, "TimeValue": 9.8076, "Time": "00:09.8076", "Line": 3, "Width": 3, "Type": 83 },
    { "Index": 99, "TimeValue": 9.8076, "Time": "00:09.8076", "Line": 9, "Width": 3, "Type": 41 },
    { "Index": 100, "TimeValue": 13.6538, "Time": "00:13.6538", "Line": 0, "Width": 3, "Type": 83 },
    { "Index": 101, "TimeValue": 13.6538, "Time": "00:13.6538", "Line": 9, "Width": 3, "Type": 41 },
    { "Index": 102, "TimeValue": 13.2692, "Time": "00:13.2692", "Line": 0, "Width": 3, "Type": 49 },
    { "Index": 103, "TimeValue": 13.0769, "Time": "00:13.0769", "Line": 6, "Width": 3, "Type": 17 },
    { "Index": 104, "TimeValue": 12.8846, "Time": "00:12.8846", "Line": 3, "Width": 3, "Type": 17 },
    { "Index": 105, "TimeValue": 12.6923, "Time": "00:12.6923", "Line": 9, "Width": 3, "Type": 17 },
    { "Index": 106, "TimeValue": 10.7692, "Time": "00:10.7692", "Line": 0, "Width": 3, "Type": 145 },
    { "Index": 107, "TimeValue": 11.5384, "Time": "00:11.5384", "Line": 0, "Width": 3, "Type": 17 },
    { "Index": 108, "TimeValue": 11.1538, "Time": "00:11.1538", "Line": 3, "Width": 3, "Type": 17 },
    { "Index": 109, "TimeValue": 12.1153, "Time": "00:12.1153", "Line": 0, "Width": 3, "Type": 37 },
    { "Index": 110, "TimeValue": 10.9615, "Time": "00:10.9615", "Line": 6, "Width": 3, "Type": 17 },
    { "Index": 111, "TimeValue": 11.7307, "Time": "00:11.7307", "Line": 6, "Width": 3, "Type": 49 },
    { "Index": 112, "TimeValue": 12.1153, "Time": "00:12.1153", "Line": 6, "Width": 3, "Type": 83 },
    { "Index": 113, "TimeValue": 11.3461, "Time": "00:11.3461", "Line": 9, "Width": 3, "Type": 17 },
    { "Index": 114, "TimeValue": 13.8461, "Time": "00:13.8461", "Line": 3, "Width": 3, "Type": 17 },
    { "Index": 115, "TimeValue": 14.2307, "Time": "00:14.2307", "Line": 0, "Width": 3, "Type": 17 },
    { "Index": 116, "TimeValue": 14.4230, "Time": "00:14.4230", "Line": 9, "Width": 3, "Type": 17 },
    { "Index": 117, "TimeValue": 14.6153, "Time": "00:14.6153", "Line": 3, "Width": 3, "Type": 17 },
    { "Index": 118, "TimeValue": 15.0000, "Time": "00:15.0000", "Line": 0, "Width": 3, "Type": 17 },
    { "Index": 119, "TimeValue": 15.1923, "Time": "00:15.1923", "Line": 9, "Width": 3, "Type": 17 },
    { "Index": 120, "TimeValue": 15.3846, "Time": "00:15.3846", "Line": 3, "Width": 3, "Type": 49 },
    { "Index": 121, "TimeValue": 15.7692, "Time": "00:15.7692", "Line": 3, "Width": 3, "Type": 131 },
    { "Index": 122, "TimeValue": 15.7692, "Time": "00:15.7692", "Line": 0, "Width": 6, "Type": 37 },
    { "Index": 123, "TimeValue": 15.7692, "Time": "00:15.7692", "Line": 6, "Width": 3, "Type": 131 },
    { "Index": 124, "TimeValue": 15.7692, "Time": "00:15.7692", "Line": 6, "Width": 6, "Type": 41 },
    { "Index": 125, "TimeValue": 15.3846, "Time": "00:15.3846", "Line": 6, "Width": 3, "Type": 49 },
    { "Index": 126, "TimeValue": 16.3461, "Time": "00:16.3461", "Line": 7, "Width": 3, "Type": 17 },
    { "Index": 127, "TimeValue": 16.5384, "Time": "00:16.5384", "Line": 7, "Width": 3, "Type": 17 },
    { "Index": 128, "TimeValue": 16.5384, "Time": "00:16.5384", "Line": 2, "Width": 3, "Type": 17 },
    { "Index": 129, "TimeValue": 16.3461, "Time": "00:16.3461", "Line": 2, "Width": 3, "Type": 17 },
    { "Index": 130, "TimeValue": 16.9230, "Time": "00:16.9230", "Line": 3, "Width": 3, "Type": 49 },
    { "Index": 131, "TimeValue": 17.5000, "Time": "00:17.5000", "Line": 0, "Width": 3, "Type": 83 },
    { "Index": 132, "TimeValue": 16.9230, "Time": "00:16.9230", "Line": 9, "Width": 3, "Type": 145 },
    { "Index": 133, "TimeValue": 18.0769, "Time": "00:18.0769", "Line": 9, "Width": 3, "Type": 83 },
    { "Index": 134, "TimeValue": 17.5000, "Time": "00:17.5000", "Line": 6, "Width": 3, "Type": 49 },
    { "Index": 135, "TimeValue": 18.6538, "Time": "00:18.6538", "Line": 0, "Width": 3, "Type": 83 },
    { "Index": 136, "TimeValue": 18.0769, "Time": "00:18.0769", "Line": 3, "Width": 3, "Type": 49 },
    { "Index": 137, "TimeValue": 18.6538, "Time": "00:18.6538", "Line": 6, "Width": 6, "Type": 41 },
    { "Index": 138, "TimeValue": 19.0384, "Time": "00:19.0384", "Line": 0, "Width": 6, "Type": 37 },
    { "Index": 139, "TimeValue": 19.4230, "Time": "00:19.4230", "Line": 6, "Width": 6, "Type": 41 },
    { "Index": 140, "TimeValue": 19.4230, "Time": "00:19.4230", "Line": 0, "Width": 6, "Type": 17 },
    { "Index": 141, "TimeValue": 20.0000, "Time": "00:20.0000", "Line": 0, "Width": 3, "Type": 145 },
    { "Index": 142, "TimeValue": 21.3461, "Time": "00:21.3461", "Line": 0, "Width": 3, "Type": 49 },
    { "Index": 143, "TimeValue": 21.9230, "Time": "00:21.9230", "Line": 3, "Width": 3, "Type": 83 },
    { "Index": 144, "TimeValue": 21.9230, "Time": "00:21.9230", "Line": 9, "Width": 3, "Type": 49 },
    { "Index": 145, "TimeValue": 22.3076, "Time": "00:22.3076", "Line": 6, "Width": 3, "Type": 83 },
    { "Index": 146, "TimeValue": 22.3076, "Time": "00:22.3076", "Line": 3, "Width": 3, "Type": 49 },
    { "Index": 147, "TimeValue": 22.6923, "Time": "00:22.6923", "Line": 0, "Width": 3, "Type": 83 },
    { "Index": 148, "TimeValue": 22.6923, "Time": "00:22.6923", "Line": 9, "Width": 3, "Type": 49 },
    { "Index": 149, "TimeValue": 23.0769, "Time": "00:23.0769", "Line": 6, "Width": 3, "Type": 83 },
    { "Index": 150, "TimeValue": 21.3461, "Time": "00:21.3461", "Line": 6, "Width": 3, "Type": 17 },
    { "Index": 151, "TimeValue": 23.0769, "Time": "00:23.0769", "Line": 3, "Width": 3, "Type": 49 },
    { "Index": 152, "TimeValue": 23.6538, "Time": "00:23.6538", "Line": 3, "Width": 3, "Type": 83 },
    { "Index": 153, "TimeValue": 23.3653, "Time": "00:23.3653", "Line": 0, "Width": 3, "Type": 130 },
    { "Index": 154, "TimeValue": 23.6538, "Time": "00:23.6538", "Line": 6, "Width": 3, "Type": 17 },
    { "Index": 155, "TimeValue": 24.1346, "Time": "00:24.1346", "Line": 9, "Width": 3, "Type": 130 },
    { "Index": 156, "TimeValue": 24.4230, "Time": "00:24.4230", "Line": 0, "Width": 3, "Type": 17 },
    { "Index": 157, "TimeValue": 25.9615, "Time": "00:25.9615", "Line": 9, "Width": 3, "Type": 49 },
    { "Index": 158, "TimeValue": 26.3461, "Time": "00:26.3461", "Line": 6, "Width": 3, "Type": 83 },
    { "Index": 159, "TimeValue": 26.3461, "Time": "00:26.3461", "Line": 3, "Width": 3, "Type": 17 },
    { "Index": 160, "TimeValue": 26.9230, "Time": "00:26.9230", "Line": 9, "Width": 3, "Type": 17 },
    { "Index": 161, "TimeValue": 26.9230, "Time": "00:26.9230", "Line": 0, "Width": 3, "Type": 49 },
    { "Index": 162, "TimeValue": 27.5000, "Time": "00:27.5000", "Line": 3, "Width": 3, "Type": 83 },
    { "Index": 163, "TimeValue": 28.4615, "Time": "00:28.4615", "Line": 6, "Width": 3, "Type": 49 },
    { "Index": 164, "TimeValue": 28.8461, "Time": "00:28.8461", "Line": 9, "Width": 3, "Type": 83 },
    { "Index": 165, "TimeValue": 28.8461, "Time": "00:28.8461", "Line": 3, "Width": 3, "Type": 49 },
    { "Index": 166, "TimeValue": 29.2307, "Time": "00:29.2307", "Line": 0, "Width": 3, "Type": 83 },
    { "Index": 167, "TimeValue": 29.8076, "Time": "00:29.8076", "Line": 3, "Width": 3, "Type": 17 },
    { "Index": 168, "TimeValue": 29.8076, "Time": "00:29.8076", "Line": 9, "Width": 3, "Type": 17 },
    { "Index": 169, "TimeValue": 30.1923, "Time": "00:30.1923", "Line": 6, "Width": 3, "Type": 17 },
    { "Index": 170, "TimeValue": 30.3846, "Time": "00:30.3846", "Line": 0, "Width": 3, "Type": 17 },
    { "Index": 171, "TimeValue": 30.5769, "Time": "00:30.5769", "Line": 6, "Width": 3, "Type": 49 },
    { "Index": 172, "TimeValue": 31.1538, "Time": "00:31.1538", "Line": 6, "Width": 3, "Type": 131 },
    { "Index": 173, "TimeValue": 30.9615, "Time": "00:30.9615", "Line": 3, "Width": 3, "Type": 49 },
    { "Index": 174, "TimeValue": 31.1538, "Time": "00:31.1538", "Line": 3, "Width": 3, "Type": 131 },
    { "Index": 175, "TimeValue": 31.1538, "Time": "00:31.1538", "Line": 0, "Width": 6, "Type": 37 },
    { "Index": 176, "TimeValue": 31.1538, "Time": "00:31.1538", "Line": 6, "Width": 6, "Type": 41 },
    { "Index": 177, "TimeValue": 32.3076, "Time": "00:32.3076", "Line": 0, "Width": 3, "Type": 145 },
    { "Index": 178, "TimeValue": 32.5000, "Time": "00:32.5000", "Line": 3, "Width": 3, "Type": 17 },
    { "Index": 179, "TimeValue": 32.8846, "Time": "00:32.8846", "Line": 0, "Width": 3, "Type": 17 },
    { "Index": 180, "TimeValue": 33.2692, "Time": "00:33.2692", "Line": 3, "Width": 3, "Type": 17 },
    { "Index": 181, "TimeValue": 32.6923, "Time": "00:32.6923", "Line": 6, "Width": 3, "Type": 17 },
    { "Index": 182, "TimeValue": 33.6538, "Time": "00:33.6538", "Line": 3, "Width": 3, "Type": 17 },
    { "Index": 183, "TimeValue": 34.2307, "Time": "00:34.2307", "Line": 6, "Width": 3, "Type": 83 },
    { "Index": 184, "TimeValue": 34.2307, "Time": "00:34.2307", "Line": 0, "Width": 3, "Type": 49 },
    { "Index": 185, "TimeValue": 34.6153, "Time": "00:34.6153", "Line": 3, "Width": 3, "Type": 83 },
    { "Index": 186, "TimeValue": 34.6153, "Time": "00:34.6153", "Line": 6, "Width": 3, "Type": 49 },
    { "Index": 187, "TimeValue": 35.0000, "Time": "00:35.0000", "Line": 0, "Width": 3, "Type": 49 },
    { "Index": 188, "TimeValue": 35.3846, "Time": "00:35.3846", "Line": 3, "Width": 3, "Type": 83 },
    { "Index": 189, "TimeValue": 35.3846, "Time": "00:35.3846", "Line": 6, "Width": 3, "Type": 49 },
    { "Index": 190, "TimeValue": 35.9615, "Time": "00:35.9615", "Line": 6, "Width": 3, "Type": 83 },
    { "Index": 191, "TimeValue": 35.9615, "Time": "00:35.9615", "Line": 3, "Width": 3, "Type": 17 },
    { "Index": 192, "TimeValue": 33.0769, "Time": "00:33.0769", "Line": 9, "Width": 3, "Type": 17 },
    { "Index": 193, "TimeValue": 32.3076, "Time": "00:32.3076", "Line": 9, "Width": 3, "Type": 145 },
    { "Index": 194, "TimeValue": 33.6538, "Time": "00:33.6538", "Line": 9, "Width": 3, "Type": 49 },
    { "Index": 195, "TimeValue": 35.0000, "Time": "00:35.0000", "Line": 9, "Width": 3, "Type": 83 },
    { "Index": 196, "TimeValue": 35.6730, "Time": "00:35.6730", "Line": 9, "Width": 3, "Type": 130 },
    { "Index": 197, "TimeValue": 36.1538, "Time": "00:36.1538", "Line": 3, "Width": 3, "Type": 49 },
    { "Index": 198, "TimeValue": 36.4423, "Time": "00:36.4423", "Line": 0, "Width": 3, "Type": 130 },
    { "Index": 199, "TimeValue": 36.7307, "Time": "00:36.7307", "Line": 3, "Width": 3, "Type": 83 },
    { "Index": 200, "TimeValue": 36.7307, "Time": "00:36.7307", "Line": 9, "Width": 3, "Type": 17 },
    { "Index": 201, "TimeValue": 38.0769, "Time": "00:38.0769", "Line": 6, "Width": 3, "Type": 17 },
    { "Index": 202, "TimeValue": 37.6923, "Time": "00:37.6923", "Line": 9, "Width": 3, "Type": 97 },
    { "Index": 203, "TimeValue": 37.8846, "Time": "00:37.8846", "Line": 3, "Width": 3, "Type": 17 },
    { "Index": 204, "TimeValue": 37.1153, "Time": "00:37.1153", "Line": 9, "Width": 3, "Type": 49 },
    { "Index": 205, "TimeValue": 37.3076, "Time": "00:37.3076", "Line": 6, "Width": 3, "Type": 83 },
    { "Index": 206, "TimeValue": 37.2435, "Time": "00:37.2435", "Line": 7, "Width": 0, "Type": 64 },
    { "Index": 207, "TimeValue": 37.1794, "Time": "00:37.1794", "Line": 7, "Width": 0, "Type": 64 },
    { "Index": 208, "TimeValue": 37.3076, "Time": "00:37.3076", "Line": 0, "Width": 3, "Type": 83 },
    { "Index": 209, "TimeValue": 37.2435, "Time": "00:37.2435", "Line": 1, "Width": 0, "Type": 64 },
    { "Index": 210, "TimeValue": 37.1794, "Time": "00:37.1794", "Line": 1, "Width": 0, "Type": 64 },
    { "Index": 211, "TimeValue": 37.1153, "Time": "00:37.1153", "Line": 3, "Width": 3, "Type": 49 },
    { "Index": 212, "TimeValue": 37.5000, "Time": "00:37.5000", "Line": 0, "Width": 3, "Type": 17 },
    { "Index": 213, "TimeValue": 38.2692, "Time": "00:38.2692", "Line": 3, "Width": 3, "Type": 17 },
    { "Index": 214, "TimeValue": 38.3653, "Time": "00:38.3653", "Line": 9, "Width": 3, "Type": 17 },
    { "Index": 215, "TimeValue": 38.4615, "Time": "00:38.4615", "Line": 3, "Width": 3, "Type": 17 },
    { "Index": 216, "TimeValue": 38.6538, "Time": "00:38.6538", "Line": 6, "Width": 3, "Type": 17 },
    { "Index": 217, "TimeValue": 38.8461, "Time": "00:38.8461", "Line": 0, "Width": 3, "Type": 17 },
    { "Index": 218, "TimeValue": 39.0384, "Time": "00:39.0384", "Line": 9, "Width": 3, "Type": 17 },
    { "Index": 219, "TimeValue": 39.2307, "Time": "00:39.2307", "Line": 3, "Width": 3, "Type": 49 },
    { "Index": 220, "TimeValue": 39.8076, "Time": "00:39.8076", "Line": 0, "Width": 3, "Type": 83 },
    { "Index": 221, "TimeValue": 39.8076, "Time": "00:39.8076", "Line": 6, "Width": 3, "Type": 17 },
    { "Index": 222, "TimeValue": 40.1923, "Time": "00:40.1923", "Line": 3, "Width": 3, "Type": 17 },
    { "Index": 223, "TimeValue": 40.2884, "Time": "00:40.2884", "Line": 6, "Width": 3, "Type": 17 },
    { "Index": 224, "TimeValue": 40.3846, "Time": "00:40.3846", "Line": 9, "Width": 3, "Type": 41 },
    { "Index": 225, "TimeValue": 40.3846, "Time": "00:40.3846", "Line": 0, "Width": 3, "Type": 37 },
    { "Index": 226, "TimeValue": 41.5384, "Time": "00:41.5384", "Line": 0, "Width": 3, "Type": 17 },
    { "Index": 227, "TimeValue": 41.9230, "Time": "00:41.9230", "Line": 3, "Width": 3, "Type": 17 },
    { "Index": 228, "TimeValue": 42.3076, "Time": "00:42.3076", "Line": 0, "Width": 3, "Type": 17 },
    { "Index": 229, "TimeValue": 42.6923, "Time": "00:42.6923", "Line": 6, "Width": 3, "Type": 17 },
    { "Index": 230, "TimeValue": 42.8846, "Time": "00:42.8846", "Line": 3, "Width": 3, "Type": 49 },
    { "Index": 231, "TimeValue": 43.2692, "Time": "00:43.2692", "Line": 0, "Width": 3, "Type": 83 },
    { "Index": 232, "TimeValue": 42.8846, "Time": "00:42.8846", "Line": 6, "Width": 3, "Type": 17 },
    { "Index": 233, "TimeValue": 43.2692, "Time": "00:43.2692", "Line": 9, "Width": 3, "Type": 17 },
    { "Index": 234, "TimeValue": 43.4615, "Time": "00:43.4615", "Line": 0, "Width": 3, "Type": 17 },
    { "Index": 235, "TimeValue": 43.6538, "Time": "00:43.6538", "Line": 6, "Width": 3, "Type": 17 },
    { "Index": 236, "TimeValue": 43.8461, "Time": "00:43.8461", "Line": 3, "Width": 3, "Type": 17 },
    { "Index": 237, "TimeValue": 44.0384, "Time": "00:44.0384", "Line": 9, "Width": 3, "Type": 17 },
    { "Index": 238, "TimeValue": 44.2307, "Time": "00:44.2307", "Line": 0, "Width": 3, "Type": 17 },
    { "Index": 239, "TimeValue": 44.6153, "Time": "00:44.6153", "Line": 9, "Width": 3, "Type": 145 },
    { "Index": 240, "TimeValue": 44.6153, "Time": "00:44.6153", "Line": 3, "Width": 3, "Type": 145 },
    { "Index": 241, "TimeValue": 45.0000, "Time": "00:45.0000", "Line": 6, "Width": 3, "Type": 49 },
    { "Index": 242, "TimeValue": 45.3846, "Time": "00:45.3846", "Line": 9, "Width": 3, "Type": 66 },
    { "Index": 243, "TimeValue": 45.7692, "Time": "00:45.7692", "Line": 6, "Width": 3, "Type": 83 },
    { "Index": 244, "TimeValue": 45.0000, "Time": "00:45.0000", "Line": 0, "Width": 3, "Type": 17 },
    { "Index": 245, "TimeValue": 45.3846, "Time": "00:45.3846", "Line": 3, "Width": 3, "Type": 17 },
    { "Index": 246, "TimeValue": 45.7692, "Time": "00:45.7692", "Line": 0, "Width": 3, "Type": 17 },
    { "Index": 247, "TimeValue": 46.1538, "Time": "00:46.1538", "Line": 3, "Width": 3, "Type": 17 },
    { "Index": 248, "TimeValue": 46.1538, "Time": "00:46.1538", "Line": 9, "Width": 3, "Type": 17 },
    { "Index": 249, "TimeValue": 46.5384, "Time": "00:46.5384", "Line": 6, "Width": 3, "Type": 17 },
    { "Index": 250, "TimeValue": 47.8846, "Time": "00:47.8846", "Line": 9, "Width": 3, "Type": 17 },
    { "Index": 251, "TimeValue": 48.0769, "Time": "00:48.0769", "Line": 3, "Width": 3, "Type": 17 },
    { "Index": 252, "TimeValue": 48.2692, "Time": "00:48.2692", "Line": 6, "Width": 3, "Type": 17 },
    { "Index": 253, "TimeValue": 48.8461, "Time": "00:48.8461", "Line": 2, "Width": 2, "Type": 17 },
    { "Index": 254, "TimeValue": 49.0384, "Time": "00:49.0384", "Line": 8, "Width": 2, "Type": 17 },
    { "Index": 255, "TimeValue": 48.4615, "Time": "00:48.4615", "Line": 0, "Width": 2, "Type": 17 },
    { "Index": 256, "TimeValue": 48.6538, "Time": "00:48.6538", "Line": 6, "Width": 2, "Type": 17 },
    { "Index": 257, "TimeValue": 49.4230, "Time": "00:49.4230", "Line": 10, "Width": 2, "Type": 17 },
    { "Index": 258, "TimeValue": 49.2307, "Time": "00:49.2307", "Line": 4, "Width": 2, "Type": 17 },
    { "Index": 259, "TimeValue": 49.6153, "Time": "00:49.6153", "Line": 2, "Width": 2, "Type": 17 },
    { "Index": 260, "TimeValue": 49.8076, "Time": "00:49.8076", "Line": 8, "Width": 2, "Type": 17 },
    { "Index": 261, "TimeValue": 50.0000, "Time": "00:50.0000", "Line": 0, "Width": 2, "Type": 17 },
    { "Index": 262, "TimeValue": 50.1923, "Time": "00:50.1923", "Line": 6, "Width": 2, "Type": 17 },
    { "Index": 263, "TimeValue": 46.7307, "Time": "00:46.7307", "Line": 3, "Width": 3, "Type": 49 },
    { "Index": 264, "TimeValue": 47.1153, "Time": "00:47.1153", "Line": 0, "Width": 3, "Type": 83 },
    { "Index": 265, "TimeValue": 46.7307, "Time": "00:46.7307", "Line": 9, "Width": 3, "Type": 17 },
    { "Index": 266, "TimeValue": 47.1153, "Time": "00:47.1153", "Line": 6, "Width": 3, "Type": 17 },
    { "Index": 267, "TimeValue": 47.3076, "Time": "00:47.3076", "Line": 3, "Width": 3, "Type": 17 },
    { "Index": 268, "TimeValue": 47.5000, "Time": "00:47.5000", "Line": 9, "Width": 3, "Type": 17 },
    { "Index": 269, "TimeValue": 50.7692, "Time": "00:50.7692", "Line": 0, "Width": 3, "Type": 145 },
    { "Index": 270, "TimeValue": 51.1538, "Time": "00:51.1538", "Line": 3, "Width": 3, "Type": 49 },
    { "Index": 271, "TimeValue": 51.5384, "Time": "00:51.5384", "Line": 0, "Width": 3, "Type": 66 },
    { "Index": 272, "TimeValue": 51.9230, "Time": "00:51.9230", "Line": 3, "Width": 3, "Type": 83 },
    { "Index": 273, "TimeValue": 52.3076, "Time": "00:52.3076", "Line": 0, "Width": 3, "Type": 17 },
    { "Index": 274, "TimeValue": 52.6923, "Time": "00:52.6923", "Line": 3, "Width": 3, "Type": 17 },
    { "Index": 275, "TimeValue": 52.8846, "Time": "00:52.8846", "Line": 0, "Width": 3, "Type": 17 },
    { "Index": 276, "TimeValue": 50.7692, "Time": "00:50.7692", "Line": 6, "Width": 3, "Type": 145 },
    { "Index": 277, "TimeValue": 51.5384, "Time": "00:51.5384", "Line": 6, "Width": 3, "Type": 17 },
    { "Index": 278, "TimeValue": 52.3076, "Time": "00:52.3076", "Line": 6, "Width": 3, "Type": 17 },
    { "Index": 279, "TimeValue": 52.8846, "Time": "00:52.8846", "Line": 6, "Width": 3, "Type": 49 },
    { "Index": 280, "TimeValue": 53.2692, "Time": "00:53.2692", "Line": 3, "Width": 3, "Type": 17 },
    { "Index": 281, "TimeValue": 53.4615, "Time": "00:53.4615", "Line": 6, "Width": 3, "Type": 17 },
    { "Index": 282, "TimeValue": 51.1538, "Time": "00:51.1538", "Line": 9, "Width": 3, "Type": 17 },
    { "Index": 283, "TimeValue": 51.9230, "Time": "00:51.9230", "Line": 9, "Width": 3, "Type": 17 },
    { "Index": 284, "TimeValue": 53.2692, "Time": "00:53.2692", "Line": 9, "Width": 3, "Type": 83 },
    { "Index": 285, "TimeValue": 53.6538, "Time": "00:53.6538", "Line": 0, "Width": 3, "Type": 17 },
    { "Index": 286, "TimeValue": 54.0384, "Time": "00:54.0384", "Line": 0, "Width": 3, "Type": 17 },
    { "Index": 287, "TimeValue": 54.2307, "Time": "00:54.2307", "Line": 6, "Width": 3, "Type": 17 },
    { "Index": 288, "TimeValue": 54.4230, "Time": "00:54.4230", "Line": 3, "Width": 3, "Type": 17 },
    { "Index": 289, "TimeValue": 55.0000, "Time": "00:55.0000", "Line": 8, "Width": 2, "Type": 17 },
    { "Index": 290, "TimeValue": 54.6153, "Time": "00:54.6153", "Line": 10, "Width": 2, "Type": 17 },
    { "Index": 291, "TimeValue": 54.8076, "Time": "00:54.8076", "Line": 4, "Width": 2, "Type": 17 },
    { "Index": 292, "TimeValue": 55.1923, "Time": "00:55.1923", "Line": 2, "Width": 2, "Type": 17 },
    { "Index": 293, "TimeValue": 55.5769, "Time": "00:55.5769", "Line": 6, "Width": 2, "Type": 17 },
    { "Index": 294, "TimeValue": 55.7692, "Time": "00:55.7692", "Line": 0, "Width": 2, "Type": 17 },
    { "Index": 295, "TimeValue": 55.9615, "Time": "00:55.9615", "Line": 8, "Width": 2, "Type": 49 },
    { "Index": 296, "TimeValue": 56.3461, "Time": "00:56.3461", "Line": 8, "Width": 2, "Type": 83 },
    { "Index": 297, "TimeValue": 56.3461, "Time": "00:56.3461", "Line": 3, "Width": 2, "Type": 17 },
    { "Index": 298, "TimeValue": 56.8269, "Time": "00:56.8269", "Line": 3, "Width": 3, "Type": 17 },
    { "Index": 299, "TimeValue": 57.3076, "Time": "00:57.3076", "Line": 3, "Width": 3, "Type": 49 },
    { "Index": 300, "TimeValue": 57.6923, "Time": "00:57.6923", "Line": 0, "Width": 3, "Type": 83 },
    { "Index": 301, "TimeValue": 57.6923, "Time": "00:57.6923", "Line": 6, "Width": 3, "Type": 49 },
    { "Index": 302, "TimeValue": 58.0769, "Time": "00:58.0769", "Line": 9, "Width": 3, "Type": 83 },
    { "Index": 303, "TimeValue": 58.0769, "Time": "00:58.0769", "Line": 3, "Width": 3, "Type": 49 },
    { "Index": 304, "TimeValue": 58.4615, "Time": "00:58.4615", "Line": 0, "Width": 3, "Type": 83 },
    { "Index": 305, "TimeValue": 58.4615, "Time": "00:58.4615", "Line": 6, "Width": 3, "Type": 49 },
    { "Index": 306, "TimeValue": 58.8461, "Time": "00:58.8461", "Line": 9, "Width": 3, "Type": 83 },
    { "Index": 307, "TimeValue": 57.3076, "Time": "00:57.3076", "Line": 9, "Width": 3, "Type": 17 },
    { "Index": 308, "TimeValue": 58.8461, "Time": "00:58.8461", "Line": 3, "Width": 3, "Type": 17 },
    { "Index": 309, "TimeValue": 59.0384, "Time": "00:59.0384", "Line": 9, "Width": 3, "Type": 17 },
    { "Index": 310, "TimeValue": 59.4230, "Time": "00:59.4230", "Line": 0, "Width": 3, "Type": 37 },
    { "Index": 311, "TimeValue": 59.4230, "Time": "00:59.4230", "Line": 6, "Width": 3, "Type": 145 },
    { "Index": 312, "TimeValue": 60.0000, "Time": "01:00.0000", "Line": 0, "Width": 3, "Type": 17 },
    { "Index": 313, "TimeValue": 60.3846, "Time": "01:00.3846", "Line": 9, "Width": 3, "Type": 49 },
    { "Index": 314, "TimeValue": 60.7692, "Time": "01:00.7692", "Line": 6, "Width": 3, "Type": 83 },
    { "Index": 315, "TimeValue": 61.1538, "Time": "01:01.1538", "Line": 3, "Width": 3, "Type": 83 },
    { "Index": 316, "TimeValue": 60.7692, "Time": "01:00.7692", "Line": 0, "Width": 3, "Type": 49 },
    { "Index": 317, "TimeValue": 61.9230, "Time": "01:01.9230", "Line": 3, "Width": 3, "Type": 83 },
    { "Index": 318, "TimeValue": 61.5384, "Time": "01:01.5384", "Line": 0, "Width": 3, "Type": 49 },
    { "Index": 319, "TimeValue": 61.5384, "Time": "01:01.5384", "Line": 6, "Width": 3, "Type": 83 },
    { "Index": 320, "TimeValue": 61.1538, "Time": "01:01.1538", "Line": 9, "Width": 3, "Type": 49 },
    { "Index": 321, "TimeValue": 62.8846, "Time": "01:02.8846", "Line": 0, "Width": 3, "Type": 37 },
    { "Index": 322, "TimeValue": 62.8846, "Time": "01:02.8846", "Line": 6, "Width": 3, "Type": 49 },
    { "Index": 323, "TimeValue": 63.6538, "Time": "01:03.6538", "Line": 6, "Width": 3, "Type": 83 },
    { "Index": 324, "TimeValue": 63.2692, "Time": "01:03.2692", "Line": 9, "Width": 3, "Type": 130 },
    { "Index": 325, "TimeValue": 64.4230, "Time": "01:04.4230", "Line": 3, "Width": 3, "Type": 83 },
    { "Index": 326, "TimeValue": 63.8461, "Time": "01:03.8461", "Line": 3, "Width": 3, "Type": 49 },
    { "Index": 327, "TimeValue": 64.1346, "Time": "01:04.1346", "Line": 0, "Width": 3, "Type": 130 },
    { "Index": 328, "TimeValue": 64.4230, "Time": "01:04.4230", "Line": 9, "Width": 3, "Type": 17 },
    { "Index": 329, "TimeValue": 65.0000, "Time": "01:05.0000", "Line": 0, "Width": 3, "Type": 17 },
    { "Index": 330, "TimeValue": 65.3846, "Time": "01:05.3846", "Line": 3, "Width": 3, "Type": 17 },
    { "Index": 331, "TimeValue": 65.7692, "Time": "01:05.7692", "Line": 6, "Width": 3, "Type": 17 },
    { "Index": 332, "TimeValue": 66.7307, "Time": "01:06.7307", "Line": 0, "Width": 4, "Type": 41 },
    { "Index": 333, "TimeValue": 69.2307, "Time": "01:09.2307", "Line": 9, "Width": 3, "Type": 17 },
    { "Index": 334, "TimeValue": 69.4230, "Time": "01:09.4230", "Line": 9, "Width": 3, "Type": 41 },
    { "Index": 335, "TimeValue": 70.0000, "Time": "01:10.0000", "Line": 6, "Width": 3, "Type": 17 },
    { "Index": 336, "TimeValue": 69.8076, "Time": "01:09.8076", "Line": 0, "Width": 3, "Type": 17 },
    { "Index": 337, "TimeValue": 70.0000, "Time": "01:10.0000", "Line": 0, "Width": 3, "Type": 37 },
    { "Index": 338, "TimeValue": 70.5769, "Time": "01:10.5769", "Line": 3, "Width": 3, "Type": 17 },
    { "Index": 339, "TimeValue": 70.3846, "Time": "01:10.3846", "Line": 3, "Width": 3, "Type": 17 },
    { "Index": 340, "TimeValue": 70.3846, "Time": "01:10.3846", "Line": 9, "Width": 3, "Type": 17 },
    { "Index": 341, "TimeValue": 70.5769, "Time": "01:10.5769", "Line": 9, "Width": 3, "Type": 41 },
    { "Index": 342, "TimeValue": 71.1538, "Time": "01:11.1538", "Line": 6, "Width": 3, "Type": 17 },
    { "Index": 343, "TimeValue": 70.9615, "Time": "01:10.9615", "Line": 6, "Width": 3, "Type": 17 },
    { "Index": 344, "TimeValue": 70.9615, "Time": "01:10.9615", "Line": 0, "Width": 3, "Type": 17 },
    { "Index": 345, "TimeValue": 71.1538, "Time": "01:11.1538", "Line": 0, "Width": 3, "Type": 37 },
    { "Index": 346, "TimeValue": 81.5384, "Time": "01:21.5384", "Line": 0, "Width": 3, "Type": 145 },
    { "Index": 347, "TimeValue": 81.5384, "Time": "01:21.5384", "Line": 9, "Width": 3, "Type": 145 },
    { "Index": 348, "TimeValue": 82.1153, "Time": "01:22.1153", "Line": 9, "Width": 3, "Type": 145 },
    { "Index": 349, "TimeValue": 82.1153, "Time": "01:22.1153", "Line": 0, "Width": 3, "Type": 145 },
    { "Index": 350, "TimeValue": 82.5000, "Time": "01:22.5000", "Line": 0, "Width": 3, "Type": 145 },
    { "Index": 351, "TimeValue": 82.5000, "Time": "01:22.5000", "Line": 9, "Width": 3, "Type": 145 },
    { "Index": 352, "TimeValue": 93.8461, "Time": "01:33.8461", "Line": 9, "Width": 3, "Type": 17 },
    { "Index": 353, "TimeValue": 94.0384, "Time": "01:34.0384", "Line": 9, "Width": 3, "Type": 17 },
    { "Index": 354, "TimeValue": 94.2307, "Time": "01:34.2307", "Line": 6, "Width": 3, "Type": 17 },
    { "Index": 355, "TimeValue": 94.4230, "Time": "01:34.4230", "Line": 6, "Width": 3, "Type": 17 },
    { "Index": 356, "TimeValue": 94.6153, "Time": "01:34.6153", "Line": 9, "Width": 3, "Type": 17 },
    { "Index": 357, "TimeValue": 94.8076, "Time": "01:34.8076", "Line": 9, "Width": 3, "Type": 17 },
    { "Index": 358, "TimeValue": 95.0000, "Time": "01:35.0000", "Line": 6, "Width": 3, "Type": 17 },
    { "Index": 359, "TimeValue": 95.1923, "Time": "01:35.1923", "Line": 6, "Width": 3, "Type": 17 },
    { "Index": 360, "TimeValue": 95.3846, "Time": "01:35.3846", "Line": 9, "Width": 3, "Type": 17 },
    { "Index": 361, "TimeValue": 93.8461, "Time": "01:33.8461", "Line": 3, "Width": 3, "Type": 49 },
    { "Index": 362, "TimeValue": 95.3846, "Time": "01:35.3846", "Line": 3, "Width": 3, "Type": 83 },
    { "Index": 363, "TimeValue": 94.6153, "Time": "01:34.6153", "Line": 0, "Width": 3, "Type": 130 },
    { "Index": 364, "TimeValue": 106.1538, "Time": "01:46.1538", "Line": 3, "Width": 6, "Type": 145 },
    { "Index": 365, "TimeValue": 101.7307, "Time": "01:41.7307", "Line": 0, "Width": 6, "Type": 37 },
    { "Index": 366, "TimeValue": 102.3076, "Time": "01:42.3076", "Line": 6, "Width": 6, "Type": 41 },
    { "Index": 367, "TimeValue": 102.8846, "Time": "01:42.8846", "Line": 0, "Width": 6, "Type": 37 },
    { "Index": 368, "TimeValue": 103.4615, "Time": "01:43.4615", "Line": 6, "Width": 6, "Type": 41 },
    { "Index": 369, "TimeValue": 103.2692, "Time": "01:43.2692", "Line": 6, "Width": 6, "Type": 17 },
    { "Index": 370, "TimeValue": 103.8461, "Time": "01:43.8461", "Line": 0, "Width": 3, "Type": 17 },
    { "Index": 371, "TimeValue": 104.0384, "Time": "01:44.0384", "Line": 3, "Width": 3, "Type": 17 },
    { "Index": 372, "TimeValue": 104.2307, "Time": "01:44.2307", "Line": 6, "Width": 3, "Type": 17 },
    { "Index": 373, "TimeValue": 104.4230, "Time": "01:44.4230", "Line": 9, "Width": 3, "Type": 49 },
    { "Index": 374, "TimeValue": 105.0000, "Time": "01:45.0000", "Line": 6, "Width": 3, "Type": 83 },
    { "Index": 375, "TimeValue": 104.4230, "Time": "01:44.4230", "Line": 3, "Width": 3, "Type": 17 },
    { "Index": 376, "TimeValue": 118.4615, "Time": "01:58.4615", "Line": 6, "Width": 6, "Type": 17 },
    { "Index": 377, "TimeValue": 118.6538, "Time": "01:58.6538", "Line": 6, "Width": 6, "Type": 41 },
    { "Index": 378, "TimeValue": 119.2307, "Time": "01:59.2307", "Line": 0, "Width": 6, "Type": 37 },
    { "Index": 379, "TimeValue": 119.0384, "Time": "01:59.0384", "Line": 0, "Width": 6, "Type": 17 },
    { "Index": 380, "TimeValue": 119.8076, "Time": "01:59.8076", "Line": 6, "Width": 6, "Type": 41 },
    { "Index": 381, "TimeValue": 119.6153, "Time": "01:59.6153", "Line": 6, "Width": 6, "Type": 17 },
    { "Index": 382, "TimeValue": 120.3846, "Time": "02:00.3846", "Line": 0, "Width": 6, "Type": 37 },
    { "Index": 383, "TimeValue": 120.1923, "Time": "02:00.1923", "Line": 0, "Width": 6, "Type": 17 },
    { "Index": 384, "TimeValue": 101.7307, "Time": "01:41.7307", "Line": 6, "Width": 6, "Type": 145 },
    { "Index": 385, "TimeValue": 102.3076, "Time": "01:42.3076", "Line": 0, "Width": 6, "Type": 145 },
    { "Index": 386, "TimeValue": 102.8846, "Time": "01:42.8846", "Line": 6, "Width": 6, "Type": 145 },
    { "Index": 387, "TimeValue": 103.4615, "Time": "01:43.4615", "Line": 0, "Width": 6, "Type": 145 },
    { "Index": 388, "TimeValue": 118.4615, "Time": "01:58.4615", "Line": 0, "Width": 3, "Type": 145 },
    { "Index": 389, "TimeValue": 118.6538, "Time": "01:58.6538", "Line": 0, "Width": 3, "Type": 145 },
    { "Index": 390, "TimeValue": 119.0384, "Time": "01:59.0384", "Line": 9, "Width": 3, "Type": 145 },
    { "Index": 391, "TimeValue": 119.2307, "Time": "01:59.2307", "Line": 9, "Width": 3, "Type": 145 },
    { "Index": 392, "TimeValue": 119.6153, "Time": "01:59.6153", "Line": 0, "Width": 3, "Type": 145 },
    { "Index": 393, "TimeValue": 119.8076, "Time": "01:59.8076", "Line": 3, "Width": 3, "Type": 145 },
    { "Index": 394, "TimeValue": 120.1923, "Time": "02:00.1923", "Line": 9, "Width": 3, "Type": 145 },
    { "Index": 395, "TimeValue": 120.3846, "Time": "02:00.3846", "Line": 6, "Width": 3, "Type": 145 },
    { "Index": 396, "TimeValue": 120.7692, "Time": "02:00.7692", "Line": 6, "Width": 3, "Type": 17 },
    { "Index": 397, "TimeValue": 121.1538, "Time": "02:01.1538", "Line": 9, "Width": 3, "Type": 17 },
    { "Index": 398, "TimeValue": 121.2500, "Time": "02:01.2500", "Line": 3, "Width": 3, "Type": 17 },
    { "Index": 399, "TimeValue": 121.3461, "Time": "02:01.3461", "Line": 6, "Width": 3, "Type": 17 },
    { "Index": 400, "TimeValue": 121.4423, "Time": "02:01.4423", "Line": 0, "Width": 3, "Type": 17 },
    { "Index": 401, "TimeValue": 121.5384, "Time": "02:01.5384", "Line": 3, "Width": 6, "Type": 17 },
    { "Index": 402, "TimeValue": 121.7307, "Time": "02:01.7307", "Line": 9, "Width": 3, "Type": 17 },
    { "Index": 403, "TimeValue": 122.1153, "Time": "02:02.1153", "Line": 0, "Width": 3, "Type": 17 },
    { "Index": 404, "TimeValue": 72.1153, "Time": "01:12.1153", "Line": 6, "Width": 3, "Type": 129 },
    { "Index": 405, "TimeValue": 73.8461, "Time": "01:13.8461", "Line": 9, "Width": 3, "Type": 83 },
    { "Index": 406, "TimeValue": 72.6923, "Time": "01:12.6923", "Line": 9, "Width": 3, "Type": 130 },
    { "Index": 407, "TimeValue": 72.6923, "Time": "01:12.6923", "Line": 0, "Width": 3, "Type": 97 },
    { "Index": 408, "TimeValue": 73.0769, "Time": "01:13.0769", "Line": 3, "Width": 3, "Type": 17 },
    { "Index": 409, "TimeValue": 73.4615, "Time": "01:13.4615", "Line": 0, "Width": 3, "Type": 17 },
    { "Index": 410, "TimeValue": 74.4230, "Time": "01:14.4230", "Line": 9, "Width": 3, "Type": 41 },
    { "Index": 411, "TimeValue": 75.1923, "Time": "01:15.1923", "Line": 6, "Width": 3, "Type": 17 },
    { "Index": 412, "TimeValue": 75.5769, "Time": "01:15.5769", "Line": 3, "Width": 3, "Type": 17 },
    { "Index": 413, "TimeValue": 75.7692, "Time": "01:15.7692", "Line": 9, "Width": 3, "Type": 49 },
    { "Index": 414, "TimeValue": 76.1538, "Time": "01:16.1538", "Line": 6, "Width": 3, "Type": 83 },
    { "Index": 415, "TimeValue": 76.1538, "Time": "01:16.1538", "Line": 0, "Width": 3, "Type": 49 },
    { "Index": 416, "TimeValue": 76.5384, "Time": "01:16.5384", "Line": 3, "Width": 3, "Type": 83 },
    { "Index": 417, "TimeValue": 76.5384, "Time": "01:16.5384", "Line": 9, "Width": 3, "Type": 17 },
    { "Index": 418, "TimeValue": 75.7692, "Time": "01:15.7692", "Line": 3, "Width": 3, "Type": 17 },
    { "Index": 419, "TimeValue": 77.1153, "Time": "01:17.1153", "Line": 3, "Width": 3, "Type": 17 },
    { "Index": 420, "TimeValue": 77.3076, "Time": "01:17.3076", "Line": 6, "Width": 3, "Type": 17 },
    { "Index": 421, "TimeValue": 77.5000, "Time": "01:17.5000", "Line": 0, "Width": 3, "Type": 17 },
    { "Index": 422, "TimeValue": 77.5000, "Time": "01:17.5000", "Line": 9, "Width": 3, "Type": 17 },
    { "Index": 423, "TimeValue": 78.0769, "Time": "01:18.0769", "Line": 6, "Width": 3, "Type": 17 },
    { "Index": 424, "TimeValue": 78.2692, "Time": "01:18.2692", "Line": 3, "Width": 3, "Type": 17 },
    { "Index": 425, "TimeValue": 78.4615, "Time": "01:18.4615", "Line": 0, "Width": 3, "Type": 17 },
    { "Index": 426, "TimeValue": 78.4615, "Time": "01:18.4615", "Line": 9, "Width": 3, "Type": 49 },
    { "Index": 427, "TimeValue": 79.0384, "Time": "01:19.0384", "Line": 6, "Width": 3, "Type": 83 },
    { "Index": 428, "TimeValue": 79.2307, "Time": "01:19.2307", "Line": 3, "Width": 3, "Type": 49 },
    { "Index": 429, "TimeValue": 80.0000, "Time": "01:20.0000", "Line": 0, "Width": 3, "Type": 83 },
    { "Index": 430, "TimeValue": 79.0384, "Time": "01:19.0384", "Line": 3, "Width": 3, "Type": 17 },
    { "Index": 431, "TimeValue": 79.2307, "Time": "01:19.2307", "Line": 6, "Width": 3, "Type": 17 },
    { "Index": 432, "TimeValue": 80.0000, "Time": "01:20.0000", "Line": 9, "Width": 3, "Type": 17 },
    { "Index": 433, "TimeValue": 80.3846, "Time": "01:20.3846", "Line": 0, "Width": 3, "Type": 17 },
    { "Index": 434, "TimeValue": 80.3846, "Time": "01:20.3846", "Line": 6, "Width": 3, "Type": 17 },
    { "Index": 435, "TimeValue": 80.7692, "Time": "01:20.7692", "Line": 3, "Width": 3, "Type": 17 },
    { "Index": 436, "TimeValue": 80.7692, "Time": "01:20.7692", "Line": 9, "Width": 3, "Type": 17 },
    { "Index": 437, "TimeValue": 81.1538, "Time": "01:21.1538", "Line": 0, "Width": 3, "Type": 17 },
    { "Index": 438, "TimeValue": 81.1538, "Time": "01:21.1538", "Line": 6, "Width": 3, "Type": 17 },
    { "Index": 439, "TimeValue": 82.8846, "Time": "01:22.8846", "Line": 6, "Width": 3, "Type": 49 },
    { "Index": 440, "TimeValue": 83.2692, "Time": "01:23.2692", "Line": 6, "Width": 3, "Type": 83 },
    { "Index": 441, "TimeValue": 83.2692, "Time": "01:23.2692", "Line": 3, "Width": 3, "Type": 17 },
    { "Index": 442, "TimeValue": 83.4615, "Time": "01:23.4615", "Line": 6, "Width": 3, "Type": 17 },
    { "Index": 443, "TimeValue": 83.6538, "Time": "01:23.6538", "Line": 9, "Width": 3, "Type": 17 },
    { "Index": 444, "TimeValue": 84.0384, "Time": "01:24.0384", "Line": 2, "Width": 2, "Type": 17 },
    { "Index": 445, "TimeValue": 84.0384, "Time": "01:24.0384", "Line": 8, "Width": 2, "Type": 17 },
    { "Index": 446, "TimeValue": 85.7692, "Time": "01:25.7692", "Line": 9, "Width": 3, "Type": 17 },
    { "Index": 447, "TimeValue": 85.3846, "Time": "01:25.3846", "Line": 6, "Width": 3, "Type": 17 },
    { "Index": 448, "TimeValue": 85.0000, "Time": "01:25.0000", "Line": 9, "Width": 3, "Type": 97 },
    { "Index": 449, "TimeValue": 84.4230, "Time": "01:24.4230", "Line": 3, "Width": 3, "Type": 145 },
    { "Index": 450, "TimeValue": 84.4230, "Time": "01:24.4230", "Line": 3, "Width": 3, "Type": 129 },
    { "Index": 451, "TimeValue": 85.0000, "Time": "01:25.0000", "Line": 0, "Width": 3, "Type": 130 },
    { "Index": 452, "TimeValue": 89.8076, "Time": "01:29.8076", "Line": 9, "Width": 3, "Type": 17 },
    { "Index": 453, "TimeValue": 88.8461, "Time": "01:28.8461", "Line": 6, "Width": 3, "Type": 83 },
    { "Index": 454, "TimeValue": 89.4230, "Time": "01:29.4230", "Line": 6, "Width": 3, "Type": 17 },
    { "Index": 455, "TimeValue": 88.4615, "Time": "01:28.4615", "Line": 9, "Width": 3, "Type": 49 },
    { "Index": 456, "TimeValue": 88.0769, "Time": "01:28.0769", "Line": 6, "Width": 3, "Type": 17 },
    { "Index": 457, "TimeValue": 87.8846, "Time": "01:27.8846", "Line": 6, "Width": 3, "Type": 17 },
    { "Index": 458, "TimeValue": 88.4615, "Time": "01:28.4615", "Line": 3, "Width": 3, "Type": 83 },
    { "Index": 459, "TimeValue": 89.6153, "Time": "01:29.6153", "Line": 3, "Width": 3, "Type": 17 },
    { "Index": 460, "TimeValue": 87.5000, "Time": "01:27.5000", "Line": 9, "Width": 3, "Type": 17 },
    { "Index": 461, "TimeValue": 87.5000, "Time": "01:27.5000", "Line": 3, "Width": 3, "Type": 17 },
    { "Index": 462, "TimeValue": 87.3076, "Time": "01:27.3076", "Line": 6, "Width": 3, "Type": 17 },
    { "Index": 463, "TimeValue": 87.1153, "Time": "01:27.1153", "Line": 3, "Width": 3, "Type": 17 },
    { "Index": 464, "TimeValue": 88.0769, "Time": "01:28.0769", "Line": 0, "Width": 3, "Type": 49 },
    { "Index": 465, "TimeValue": 88.8461, "Time": "01:28.8461", "Line": 0, "Width": 3, "Type": 17 },
    { "Index": 466, "TimeValue": 89.8076, "Time": "01:29.8076", "Line": 0, "Width": 3, "Type": 17 },
    { "Index": 467, "TimeValue": 86.7307, "Time": "01:26.7307", "Line": 9, "Width": 3, "Type": 83 },
    { "Index": 468, "TimeValue": 86.7307, "Time": "01:26.7307", "Line": 0, "Width": 3, "Type": 37 },
    { "Index": 469, "TimeValue": 86.5384, "Time": "01:26.5384", "Line": 3, "Width": 3, "Type": 17 },
    { "Index": 470, "TimeValue": 86.1538, "Time": "01:26.1538", "Line": 6, "Width": 3, "Type": 49 },
    { "Index": 471, "TimeValue": 86.1538, "Time": "01:26.1538", "Line": 0, "Width": 3, "Type": 83 },
    { "Index": 472, "TimeValue": 90.3846, "Time": "01:30.3846", "Line": 3, "Width": 3, "Type": 17 },
    { "Index": 473, "TimeValue": 90.5769, "Time": "01:30.5769", "Line": 6, "Width": 3, "Type": 17 },
    { "Index": 474, "TimeValue": 90.7692, "Time": "01:30.7692", "Line": 9, "Width": 3, "Type": 41 },
    { "Index": 475, "TimeValue": 90.7692, "Time": "01:30.7692", "Line": 0, "Width": 3, "Type": 17 },
    { "Index": 476, "TimeValue": 90.9615, "Time": "01:30.9615", "Line": 3, "Width": 3, "Type": 17 },
    { "Index": 477, "TimeValue": 91.1538, "Time": "01:31.1538", "Line": 6, "Width": 3, "Type": 17 },
    { "Index": 478, "TimeValue": 91.3461, "Time": "01:31.3461", "Line": 0, "Width": 3, "Type": 37 },
    { "Index": 479, "TimeValue": 91.3461, "Time": "01:31.3461", "Line": 9, "Width": 3, "Type": 17 },
    { "Index": 480, "TimeValue": 91.7307, "Time": "01:31.7307", "Line": 9, "Width": 3, "Type": 41 },
    { "Index": 481, "TimeValue": 91.7307, "Time": "01:31.7307", "Line": 0, "Width": 3, "Type": 17 },
    { "Index": 482, "TimeValue": 91.9230, "Time": "01:31.9230", "Line": 3, "Width": 3, "Type": 17 },
    { "Index": 483, "TimeValue": 92.3076, "Time": "01:32.3076", "Line": 3, "Width": 3, "Type": 17 },
    { "Index": 484, "TimeValue": 92.5000, "Time": "01:32.5000", "Line": 9, "Width": 3, "Type": 17 },
    { "Index": 485, "TimeValue": 92.5000, "Time": "01:32.5000", "Line": 0, "Width": 3, "Type": 37 },
    { "Index": 486, "TimeValue": 92.8846, "Time": "01:32.8846", "Line": 6, "Width": 3, "Type": 17 },
    { "Index": 487, "TimeValue": 93.0769, "Time": "01:33.0769", "Line": 3, "Width": 3, "Type": 17 },
    { "Index": 488, "TimeValue": 93.4615, "Time": "01:33.4615", "Line": 0, "Width": 3, "Type": 17 },
    { "Index": 489, "TimeValue": 93.0769, "Time": "01:33.0769", "Line": 6, "Width": 3, "Type": 49 },
    { "Index": 490, "TimeValue": 93.4615, "Time": "01:33.4615", "Line": 6, "Width": 3, "Type": 83 },
    { "Index": 491, "TimeValue": 93.2692, "Time": "01:33.2692", "Line": 9, "Width": 3, "Type": 130 },
    { "Index": 492, "TimeValue": 96.1538, "Time": "01:36.1538", "Line": 9, "Width": 3, "Type": 49 },
    { "Index": 493, "TimeValue": 96.5384, "Time": "01:36.5384", "Line": 6, "Width": 3, "Type": 83 },
    { "Index": 494, "TimeValue": 96.5384, "Time": "01:36.5384", "Line": 0, "Width": 3, "Type": 49 },
    { "Index": 495, "TimeValue": 96.9230, "Time": "01:36.9230", "Line": 3, "Width": 3, "Type": 83 },
    { "Index": 496, "TimeValue": 97.3076, "Time": "01:37.3076", "Line": 6, "Width": 3, "Type": 83 },
    { "Index": 497, "TimeValue": 96.9230, "Time": "01:36.9230", "Line": 9, "Width": 3, "Type": 49 },
    { "Index": 498, "TimeValue": 97.8846, "Time": "01:37.8846", "Line": 3, "Width": 3, "Type": 17 },
    { "Index": 499, "TimeValue": 98.0769, "Time": "01:38.0769", "Line": 6, "Width": 3, "Type": 17 },
    { "Index": 500, "TimeValue": 98.2692, "Time": "01:38.2692", "Line": 3, "Width": 3, "Type": 17 },
    { "Index": 501, "TimeValue": 98.4615, "Time": "01:38.4615", "Line": 0, "Width": 3, "Type": 17 },
    { "Index": 502, "TimeValue": 98.4615, "Time": "01:38.4615", "Line": 9, "Width": 3, "Type": 17 },
    { "Index": 503, "TimeValue": 98.8461, "Time": "01:38.8461", "Line": 3, "Width": 3, "Type": 17 },
    { "Index": 504, "TimeValue": 98.6538, "Time": "01:38.6538", "Line": 6, "Width": 3, "Type": 17 },
    { "Index": 505, "TimeValue": 99.0384, "Time": "01:39.0384", "Line": 0, "Width": 3, "Type": 17 },
    { "Index": 506, "TimeValue": 99.2307, "Time": "01:39.2307", "Line": 6, "Width": 3, "Type": 49 },
    { "Index": 507, "TimeValue": 100.0000, "Time": "01:40.0000", "Line": 6, "Width": 3, "Type": 43 },
    { "Index": 508, "TimeValue": 99.6153, "Time": "01:39.6153", "Line": 3, "Width": 3, "Type": 49 },
    { "Index": 509, "TimeValue": 100.0000, "Time": "01:40.0000", "Line": 3, "Width": 3, "Type": 39 },
    { "Index": 510, "TimeValue": 100.5769, "Time": "01:40.5769", "Line": 9, "Width": 3, "Type": 17 },
    { "Index": 511, "TimeValue": 100.7692, "Time": "01:40.7692", "Line": 8, "Width": 3, "Type": 17 },
    { "Index": 512, "TimeValue": 100.9615, "Time": "01:40.9615", "Line": 7, "Width": 3, "Type": 17 },
    { "Index": 513, "TimeValue": 100.5769, "Time": "01:40.5769", "Line": 0, "Width": 3, "Type": 17 },
    { "Index": 514, "TimeValue": 100.7692, "Time": "01:40.7692", "Line": 1, "Width": 3, "Type": 17 },
    { "Index": 515, "TimeValue": 100.9615, "Time": "01:40.9615", "Line": 2, "Width": 3, "Type": 17 },
    { "Index": 516, "TimeValue": 105.0000, "Time": "01:45.0000", "Line": 0, "Width": 3, "Type": 49 },
    { "Index": 517, "TimeValue": 105.3846, "Time": "01:45.3846", "Line": 3, "Width": 3, "Type": 83 },
    { "Index": 518, "TimeValue": 105.1923, "Time": "01:45.1923", "Line": 0, "Width": 0, "Type": 64 },
    { "Index": 519, "TimeValue": 105.0961, "Time": "01:45.0961", "Line": 1, "Width": 0, "Type": 64 },
    { "Index": 520, "TimeValue": 105.2884, "Time": "01:45.2884", "Line": 1, "Width": 0, "Type": 64 },
    { "Index": 521, "TimeValue": 105.5769, "Time": "01:45.5769", "Line": 0, "Width": 0, "Type": 64 },
    { "Index": 522, "TimeValue": 105.6730, "Time": "01:45.6730", "Line": 7, "Width": 0, "Type": 64 },
    { "Index": 523, "TimeValue": 105.4807, "Time": "01:45.4807", "Line": 7, "Width": 0, "Type": 64 },
    { "Index": 524, "TimeValue": 105.3846, "Time": "01:45.3846", "Line": 6, "Width": 3, "Type": 49 },
    { "Index": 525, "TimeValue": 105.7692, "Time": "01:45.7692", "Line": 9, "Width": 3, "Type": 83 },
    { "Index": 526, "TimeValue": 106.5384, "Time": "01:46.5384", "Line": 3, "Width": 3, "Type": 17 },
    { "Index": 527, "TimeValue": 106.7307, "Time": "01:46.7307", "Line": 6, "Width": 3, "Type": 17 },
    { "Index": 528, "TimeValue": 107.1153, "Time": "01:47.1153", "Line": 6, "Width": 3, "Type": 17 },
    { "Index": 529, "TimeValue": 106.9230, "Time": "01:46.9230", "Line": 0, "Width": 3, "Type": 17 },
    { "Index": 530, "TimeValue": 107.1153, "Time": "01:47.1153", "Line": 0, "Width": 3, "Type": 49 },
    { "Index": 531, "TimeValue": 107.5000, "Time": "01:47.5000", "Line": 0, "Width": 3, "Type": 83 },
    { "Index": 532, "TimeValue": 107.5000, "Time": "01:47.5000", "Line": 9, "Width": 3, "Type": 17 },
    { "Index": 533, "TimeValue": 109.0384, "Time": "01:49.0384", "Line": 9, "Width": 3, "Type": 83 },
    { "Index": 534, "TimeValue": 108.6538, "Time": "01:48.6538", "Line": 3, "Width": 3, "Type": 17 },
    { "Index": 535, "TimeValue": 108.6538, "Time": "01:48.6538", "Line": 9, "Width": 3, "Type": 49 },
    { "Index": 536, "TimeValue": 109.0384, "Time": "01:49.0384", "Line": 0, "Width": 3, "Type": 17 },
    { "Index": 537, "TimeValue": 108.4615, "Time": "01:48.4615", "Line": 9, "Width": 3, "Type": 17 },
    { "Index": 538, "TimeValue": 108.0769, "Time": "01:48.0769", "Line": 6, "Width": 3, "Type": 17 },
    { "Index": 539, "TimeValue": 108.2692, "Time": "01:48.2692", "Line": 3, "Width": 3, "Type": 17 },
    { "Index": 540, "TimeValue": 109.6153, "Time": "01:49.6153", "Line": 6, "Width": 3, "Type": 17 },
    { "Index": 541, "TimeValue": 109.8076, "Time": "01:49.8076", "Line": 3, "Width": 3, "Type": 17 },
    { "Index": 542, "TimeValue": 110.0000, "Time": "01:50.0000", "Line": 9, "Width": 3, "Type": 17 },
    { "Index": 543, "TimeValue": 110.1923, "Time": "01:50.1923", "Line": 6, "Width": 3, "Type": 17 },
    { "Index": 544, "TimeValue": 110.3846, "Time": "01:50.3846", "Line": 3, "Width": 3, "Type": 17 },
    { "Index": 545, "TimeValue": 110.5769, "Time": "01:50.5769", "Line": 0, "Width": 3, "Type": 17 },
    { "Index": 546, "TimeValue": 109.4230, "Time": "01:49.4230", "Line": 3, "Width": 3, "Type": 17 },
    { "Index": 547, "TimeValue": 110.7692, "Time": "01:50.7692", "Line": 0, "Width": 3, "Type": 49 },
    { "Index": 548, "TimeValue": 111.3461, "Time": "01:51.3461", "Line": 3, "Width": 3, "Type": 131 },
    { "Index": 549, "TimeValue": 110.9615, "Time": "01:50.9615", "Line": 3, "Width": 3, "Type": 130 },
    { "Index": 550, "TimeValue": 111.3461, "Time": "01:51.3461", "Line": 0, "Width": 6, "Type": 37 },
    { "Index": 551, "TimeValue": 111.3461, "Time": "01:51.3461", "Line": 6, "Width": 3, "Type": 131 },
    { "Index": 552, "TimeValue": 111.3461, "Time": "01:51.3461", "Line": 6, "Width": 6, "Type": 41 },
    { "Index": 553, "TimeValue": 110.9615, "Time": "01:50.9615", "Line": 6, "Width": 3, "Type": 130 },
    { "Index": 554, "TimeValue": 110.7692, "Time": "01:50.7692", "Line": 9, "Width": 3, "Type": 49 },
    { "Index": 555, "TimeValue": 111.9230, "Time": "01:51.9230", "Line": 0, "Width": 3, "Type": 49 },
    { "Index": 556, "TimeValue": 112.3076, "Time": "01:52.3076", "Line": 3, "Width": 3, "Type": 83 },
    { "Index": 557, "TimeValue": 112.1153, "Time": "01:52.1153", "Line": 0, "Width": 0, "Type": 64 },
    { "Index": 558, "TimeValue": 112.2115, "Time": "01:52.2115", "Line": 2, "Width": 0, "Type": 64 },
    { "Index": 559, "TimeValue": 112.0192, "Time": "01:52.0192", "Line": 0, "Width": 0, "Type": 64 },
    { "Index": 560, "TimeValue": 112.3076, "Time": "01:52.3076", "Line": 9, "Width": 3, "Type": 145 },
    { "Index": 561, "TimeValue": 112.5000, "Time": "01:52.5000", "Line": 0, "Width": 3, "Type": 17 },
    { "Index": 562, "TimeValue": 112.8846, "Time": "01:52.8846", "Line": 3, "Width": 3, "Type": 17 },
    { "Index": 563, "TimeValue": 113.2692, "Time": "01:53.2692", "Line": 3, "Width": 3, "Type": 17 },
    { "Index": 564, "TimeValue": 113.6538, "Time": "01:53.6538", "Line": 0, "Width": 3, "Type": 17 },
    { "Index": 565, "TimeValue": 112.6923, "Time": "01:52.6923", "Line": 6, "Width": 3, "Type": 17 },
    { "Index": 566, "TimeValue": 114.2307, "Time": "01:54.2307", "Line": 3, "Width": 3, "Type": 17 },
    { "Index": 567, "TimeValue": 114.4230, "Time": "01:54.4230", "Line": 6, "Width": 3, "Type": 17 },
    { "Index": 568, "TimeValue": 114.6153, "Time": "01:54.6153", "Line": 0, "Width": 3, "Type": 17 },
    { "Index": 569, "TimeValue": 114.8076, "Time": "01:54.8076", "Line": 6, "Width": 3, "Type": 17 },
    { "Index": 570, "TimeValue": 114.8076, "Time": "01:54.8076", "Line": 0, "Width": 3, "Type": 49 },
    { "Index": 571, "TimeValue": 115.1923, "Time": "01:55.1923", "Line": 3, "Width": 3, "Type": 83 },
    { "Index": 572, "TimeValue": 113.0769, "Time": "01:53.0769", "Line": 9, "Width": 3, "Type": 17 },
    { "Index": 573, "TimeValue": 113.2692, "Time": "01:53.2692", "Line": 9, "Width": 3, "Type": 49 },
    { "Index": 574, "TimeValue": 113.6538, "Time": "01:53.6538", "Line": 6, "Width": 3, "Type": 83 },
    { "Index": 575, "TimeValue": 115.1923, "Time": "01:55.1923", "Line": 9, "Width": 3, "Type": 17 },
    { "Index": 576, "TimeValue": 116.7307, "Time": "01:56.7307", "Line": 9, "Width": 3, "Type": 17 },
    { "Index": 577, "TimeValue": 116.5384, "Time": "01:56.5384", "Line": 6, "Width": 3, "Type": 17 },
    { "Index": 578, "TimeValue": 115.9615, "Time": "01:55.9615", "Line": 6, "Width": 3, "Type": 17 },
    { "Index": 579, "TimeValue": 116.3461, "Time": "01:56.3461", "Line": 3, "Width": 3, "Type": 17 },
    { "Index": 580, "TimeValue": 115.7692, "Time": "01:55.7692", "Line": 3, "Width": 3, "Type": 17 },
    { "Index": 581, "TimeValue": 116.1538, "Time": "01:56.1538", "Line": 0, "Width": 3, "Type": 17 },
    { "Index": 582, "TimeValue": 115.5769, "Time": "01:55.5769", "Line": 6, "Width": 3, "Type": 17 },
    { "Index": 583, "TimeValue": 117.1153, "Time": "01:57.1153", "Line": 3, "Width": 3, "Type": 130 },
    { "Index": 584, "TimeValue": 116.9230, "Time": "01:56.9230", "Line": 0, "Width": 3, "Type": 49 },
    { "Index": 585, "TimeValue": 117.3076, "Time": "01:57.3076", "Line": 0, "Width": 3, "Type": 39 },
    { "Index": 586, "TimeValue": 117.3076, "Time": "01:57.3076", "Line": 9, "Width": 3, "Type": 43 },
    { "Index": 587, "TimeValue": 117.1153, "Time": "01:57.1153", "Line": 6, "Width": 3, "Type": 130 },
    { "Index": 588, "TimeValue": 116.9230, "Time": "01:56.9230", "Line": 9, "Width": 3, "Type": 49 },
    { "Index": 589, "TimeValue": 123.4615, "Time": "02:03.4615", "Line": 3, "Width": 3, "Type": 130 },
    { "Index": 590, "TimeValue": 124.6153, "Time": "02:04.6153", "Line": 3, "Width": 3, "Type": 130 },
    { "Index": 591, "TimeValue": 124.0384, "Time": "02:04.0384", "Line": 0, "Width": 3, "Type": 130 },
    { "Index": 592, "TimeValue": 125.9615, "Time": "02:05.9615", "Line": 0, "Width": 3, "Type": 130 },
    { "Index": 593, "TimeValue": 125.9615, "Time": "02:05.9615", "Line": 9, "Width": 3, "Type": 130 },
    { "Index": 594, "TimeValue": 126.5384, "Time": "02:06.5384", "Line": 6, "Width": 3, "Type": 83 },
    { "Index": 595, "TimeValue": 124.6153, "Time": "02:04.6153", "Line": 6, "Width": 3, "Type": 130 },
    { "Index": 596, "TimeValue": 124.0384, "Time": "02:04.0384", "Line": 9, "Width": 3, "Type": 130 },
    { "Index": 597, "TimeValue": 123.4615, "Time": "02:03.4615", "Line": 6, "Width": 3, "Type": 130 },
    { "Index": 598, "TimeValue": 122.3076, "Time": "02:02.3076", "Line": 6, "Width": 3, "Type": 49 },
    { "Index": 599, "TimeValue": 84.4230, "Time": "01:24.4230", "Line": 9, "Width": 3, "Type": 145 },
    { "Index": 600, "TimeValue": 19.0384, "Time": "00:19.0384", "Line": 6, "Width": 6, "Type": 17 },
    { "Index": 601, "TimeValue": 71.5384, "Time": "01:11.5384", "Line": 10, "Width": 2, "Type": 49 },
    { "Index": 602, "TimeValue": 71.9230, "Time": "01:11.9230", "Line": 6, "Width": 2, "Type": 83 },
    { "Index": 603, "TimeValue": 71.8589, "Time": "01:11.8589", "Line": 7, "Width": 0, "Type": 64 },
    { "Index": 604, "TimeValue": 71.7948, "Time": "01:11.7948", "Line": 8, "Width": 0, "Type": 64 },
    { "Index": 605, "TimeValue": 71.7307, "Time": "01:11.7307", "Line": 8, "Width": 0, "Type": 64 },
    { "Index": 606, "TimeValue": 71.6666, "Time": "01:11.6666", "Line": 8, "Width": 0, "Type": 64 },
    { "Index": 607, "TimeValue": 71.6025, "Time": "01:11.6025", "Line": 9, "Width": 0, "Type": 64 },
    { "Index": 608, "TimeValue": 71.9230, "Time": "01:11.9230", "Line": 0, "Width": 2, "Type": 83 },
    { "Index": 609, "TimeValue": 71.8589, "Time": "01:11.8589", "Line": 1, "Width": 0, "Type": 64 },
    { "Index": 610, "TimeValue": 71.7948, "Time": "01:11.7948", "Line": 2, "Width": 0, "Type": 64 },
    { "Index": 611, "TimeValue": 71.7307, "Time": "01:11.7307", "Line": 2, "Width": 0, "Type": 64 },
    { "Index": 612, "TimeValue": 71.6666, "Time": "01:11.6666", "Line": 2, "Width": 0, "Type": 64 },
    { "Index": 613, "TimeValue": 71.6025, "Time": "01:11.6025", "Line": 3, "Width": 0, "Type": 64 },
    { "Index": 614, "TimeValue": 71.5384, "Time": "01:11.5384", "Line": 4, "Width": 2, "Type": 49 },
    { "Index": 615, "TimeValue": 66.1538, "Time": "01:06.1538", "Line": 3, "Width": 3, "Type": 145 },
    { "Index": 616, "TimeValue": 66.1538, "Time": "01:06.1538", "Line": 9, "Width": 3, "Type": 145 },
    { "Index": 617, "TimeValue": 67.5000, "Time": "01:07.5000", "Line": 8, "Width": 4, "Type": 37 },
    { "Index": 618, "TimeValue": 67.6923, "Time": "01:07.6923", "Line": 2, "Width": 4, "Type": 37 },
    { "Index": 619, "TimeValue": 68.2692, "Time": "01:08.2692", "Line": 0, "Width": 4, "Type": 41 },
    { "Index": 620, "TimeValue": 68.4615, "Time": "01:08.4615", "Line": 6, "Width": 4, "Type": 41 },
    { "Index": 621, "TimeValue": 72.1153, "Time": "01:12.1153", "Line": 0, "Width": 3, "Type": 145 },
    { "Index": 622, "TimeValue": 41.7307, "Time": "00:41.7307", "Line": 0, "Width": 0, "Type": 112 },
    { "Index": 623, "TimeValue": 41.9230, "Time": "00:41.9230", "Line": 0, "Width": 0, "Type": 112 },
    { "Index": 624, "TimeValue": 42.1153, "Time": "00:42.1153", "Line": 0, "Width": 0, "Type": 112 },
    { "Index": 625, "TimeValue": 74.0384, "Time": "01:14.0384", "Line": 0, "Width": 0, "Type": 112 },
    { "Index": 626, "TimeValue": 74.2307, "Time": "01:14.2307", "Line": 0, "Width": 0, "Type": 112 },
    { "Index": 627, "TimeValue": 120.9615, "Time": "02:00.9615", "Line": 0, "Width": 0, "Type": 112 },
    { "Index": 628, "TimeValue": 5.7692, "Time": "00:05.7692", "Line": 0, "Width": 0, "Type": 112 },
    { "Index": 629, "TimeValue": 7.3076, "Time": "00:07.3076", "Line": 0, "Width": 0, "Type": 112 },
    { "Index": 630, "TimeValue": 9.6153, "Time": "00:09.6153", "Line": 0, "Width": 0, "Type": 112 },
    { "Index": 631, "TimeValue": 11.9230, "Time": "00:11.9230", "Line": 0, "Width": 0, "Type": 112 },
    { "Index": 632, "TimeValue": 13.4615, "Time": "00:13.4615", "Line": 0, "Width": 0, "Type": 112 },
    { "Index": 633, "TimeValue": 15.5769, "Time": "00:15.5769", "Line": 0, "Width": 0, "Type": 112 },
    { "Index": 634, "TimeValue": 15.5769, "Time": "00:15.5769", "Line": 0, "Width": 0, "Type": 112 },
    { "Index": 635, "TimeValue": 17.1153, "Time": "00:17.1153", "Line": 0, "Width": 0, "Type": 112 },
    { "Index": 636, "TimeValue": 17.3076, "Time": "00:17.3076", "Line": 0, "Width": 0, "Type": 112 },
    { "Index": 637, "TimeValue": 17.6923, "Time": "00:17.6923", "Line": 0, "Width": 0, "Type": 112 },
    { "Index": 638, "TimeValue": 17.8846, "Time": "00:17.8846", "Line": 0, "Width": 0, "Type": 112 },
    { "Index": 639, "TimeValue": 18.2692, "Time": "00:18.2692", "Line": 0, "Width": 0, "Type": 112 },
    { "Index": 640, "TimeValue": 18.4615, "Time": "00:18.4615", "Line": 0, "Width": 0, "Type": 112 },
    { "Index": 641, "TimeValue": 21.5384, "Time": "00:21.5384", "Line": 0, "Width": 0, "Type": 112 },
    { "Index": 642, "TimeValue": 21.7307, "Time": "00:21.7307", "Line": 0, "Width": 0, "Type": 112 },
    { "Index": 643, "TimeValue": 22.1153, "Time": "00:22.1153", "Line": 0, "Width": 0, "Type": 112 },
    { "Index": 644, "TimeValue": 22.5000, "Time": "00:22.5000", "Line": 0, "Width": 0, "Type": 112 },
    { "Index": 645, "TimeValue": 22.8846, "Time": "00:22.8846", "Line": 0, "Width": 0, "Type": 112 },
    { "Index": 646, "TimeValue": 23.2692, "Time": "00:23.2692", "Line": 0, "Width": 0, "Type": 112 },
    { "Index": 647, "TimeValue": 23.4615, "Time": "00:23.4615", "Line": 0, "Width": 0, "Type": 112 },
    { "Index": 648, "TimeValue": 24.0384, "Time": "00:24.0384", "Line": 0, "Width": 0, "Type": 112 },
    { "Index": 649, "TimeValue": 24.2307, "Time": "00:24.2307", "Line": 0, "Width": 0, "Type": 112 },
    { "Index": 650, "TimeValue": 26.1538, "Time": "00:26.1538", "Line": 0, "Width": 0, "Type": 112 },
    { "Index": 651, "TimeValue": 27.1153, "Time": "00:27.1153", "Line": 0, "Width": 0, "Type": 112 },
    { "Index": 652, "TimeValue": 27.3076, "Time": "00:27.3076", "Line": 0, "Width": 0, "Type": 112 },
    { "Index": 653, "TimeValue": 28.6538, "Time": "00:28.6538", "Line": 0, "Width": 0, "Type": 112 },
    { "Index": 654, "TimeValue": 29.0384, "Time": "00:29.0384", "Line": 0, "Width": 0, "Type": 112 },
    { "Index": 655, "TimeValue": 30.7692, "Time": "00:30.7692", "Line": 0, "Width": 0, "Type": 112 },
    { "Index": 656, "TimeValue": 30.9615, "Time": "00:30.9615", "Line": 0, "Width": 0, "Type": 112 },
    { "Index": 657, "TimeValue": 33.8461, "Time": "00:33.8461", "Line": 0, "Width": 0, "Type": 112 },
    { "Index": 658, "TimeValue": 34.0384, "Time": "00:34.0384", "Line": 0, "Width": 0, "Type": 112 },
    { "Index": 659, "TimeValue": 34.4230, "Time": "00:34.4230", "Line": 0, "Width": 0, "Type": 112 },
    { "Index": 660, "TimeValue": 34.8076, "Time": "00:34.8076", "Line": 0, "Width": 0, "Type": 112 },
    { "Index": 661, "TimeValue": 35.1923, "Time": "00:35.1923", "Line": 0, "Width": 0, "Type": 112 },
    { "Index": 662, "TimeValue": 35.5769, "Time": "00:35.5769", "Line": 0, "Width": 0, "Type": 112 },
    { "Index": 663, "TimeValue": 35.7692, "Time": "00:35.7692", "Line": 0, "Width": 0, "Type": 112 },
    { "Index": 664, "TimeValue": 36.3461, "Time": "00:36.3461", "Line": 0, "Width": 0, "Type": 112 },
    { "Index": 665, "TimeValue": 36.5384, "Time": "00:36.5384", "Line": 0, "Width": 0, "Type": 112 },
    { "Index": 666, "TimeValue": 39.4230, "Time": "00:39.4230", "Line": 0, "Width": 0, "Type": 112 },
    { "Index": 667, "TimeValue": 39.6153, "Time": "00:39.6153", "Line": 0, "Width": 0, "Type": 112 },
    { "Index": 668, "TimeValue": 43.0769, "Time": "00:43.0769", "Line": 0, "Width": 0, "Type": 112 },
    { "Index": 669, "TimeValue": 45.1923, "Time": "00:45.1923", "Line": 0, "Width": 0, "Type": 112 },
    { "Index": 670, "TimeValue": 45.5769, "Time": "00:45.5769", "Line": 0, "Width": 0, "Type": 112 },
    { "Index": 671, "TimeValue": 46.9230, "Time": "00:46.9230", "Line": 0, "Width": 0, "Type": 112 },
    { "Index": 672, "TimeValue": 51.3461, "Time": "00:51.3461", "Line": 0, "Width": 0, "Type": 112 },
    { "Index": 673, "TimeValue": 51.7307, "Time": "00:51.7307", "Line": 0, "Width": 0, "Type": 112 },
    { "Index": 674, "TimeValue": 53.0769, "Time": "00:53.0769", "Line": 0, "Width": 0, "Type": 112 },
    { "Index": 675, "TimeValue": 56.1538, "Time": "00:56.1538", "Line": 0, "Width": 0, "Type": 112 },
    { "Index": 676, "TimeValue": 57.5000, "Time": "00:57.5000", "Line": 0, "Width": 0, "Type": 112 },
    { "Index": 677, "TimeValue": 57.8846, "Time": "00:57.8846", "Line": 0, "Width": 0, "Type": 112 },
    { "Index": 678, "TimeValue": 58.2692, "Time": "00:58.2692", "Line": 0, "Width": 0, "Type": 112 },
    { "Index": 679, "TimeValue": 58.6538, "Time": "00:58.6538", "Line": 0, "Width": 0, "Type": 112 },
    { "Index": 680, "TimeValue": 60.5769, "Time": "01:00.5769", "Line": 0, "Width": 0, "Type": 112 },
    { "Index": 681, "TimeValue": 60.9615, "Time": "01:00.9615", "Line": 0, "Width": 0, "Type": 112 },
    { "Index": 682, "TimeValue": 61.7307, "Time": "01:01.7307", "Line": 0, "Width": 0, "Type": 112 },
    { "Index": 683, "TimeValue": 61.3461, "Time": "01:01.3461", "Line": 0, "Width": 0, "Type": 112 },
    { "Index": 684, "TimeValue": 63.0769, "Time": "01:03.0769", "Line": 0, "Width": 0, "Type": 112 },
    { "Index": 685, "TimeValue": 63.2692, "Time": "01:03.2692", "Line": 0, "Width": 0, "Type": 112 },
    { "Index": 686, "TimeValue": 63.4615, "Time": "01:03.4615", "Line": 0, "Width": 0, "Type": 112 },
    { "Index": 687, "TimeValue": 64.0384, "Time": "01:04.0384", "Line": 0, "Width": 0, "Type": 112 },
    { "Index": 688, "TimeValue": 64.2307, "Time": "01:04.2307", "Line": 0, "Width": 0, "Type": 112 },
    { "Index": 689, "TimeValue": 94.0384, "Time": "01:34.0384", "Line": 0, "Width": 0, "Type": 112 },
    { "Index": 690, "TimeValue": 94.2307, "Time": "01:34.2307", "Line": 0, "Width": 0, "Type": 112 },
    { "Index": 691, "TimeValue": 94.4230, "Time": "01:34.4230", "Line": 0, "Width": 0, "Type": 112 },
    { "Index": 692, "TimeValue": 94.6153, "Time": "01:34.6153", "Line": 0, "Width": 0, "Type": 112 },
    { "Index": 693, "TimeValue": 94.8076, "Time": "01:34.8076", "Line": 0, "Width": 0, "Type": 112 },
    { "Index": 694, "TimeValue": 95.0000, "Time": "01:35.0000", "Line": 0, "Width": 0, "Type": 112 },
    { "Index": 695, "TimeValue": 95.1923, "Time": "01:35.1923", "Line": 0, "Width": 0, "Type": 112 },
    { "Index": 696, "TimeValue": 104.6153, "Time": "01:44.6153", "Line": 0, "Width": 0, "Type": 112 },
    { "Index": 697, "TimeValue": 104.8076, "Time": "01:44.8076", "Line": 0, "Width": 0, "Type": 112 },
    { "Index": 698, "TimeValue": 72.3076, "Time": "01:12.3076", "Line": 0, "Width": 0, "Type": 112 },
    { "Index": 699, "TimeValue": 72.5000, "Time": "01:12.5000", "Line": 0, "Width": 0, "Type": 112 },
    { "Index": 700, "TimeValue": 72.6923, "Time": "01:12.6923", "Line": 0, "Width": 0, "Type": 112 },
    { "Index": 701, "TimeValue": 72.8846, "Time": "01:12.8846", "Line": 0, "Width": 0, "Type": 112 },
    { "Index": 702, "TimeValue": 73.0769, "Time": "01:13.0769", "Line": 0, "Width": 0, "Type": 112 },
    { "Index": 703, "TimeValue": 73.2692, "Time": "01:13.2692", "Line": 0, "Width": 0, "Type": 112 },
    { "Index": 704, "TimeValue": 73.4615, "Time": "01:13.4615", "Line": 0, "Width": 0, "Type": 112 },
    { "Index": 705, "TimeValue": 73.6538, "Time": "01:13.6538", "Line": 0, "Width": 0, "Type": 112 },
    { "Index": 706, "TimeValue": 75.9615, "Time": "01:15.9615", "Line": 0, "Width": 0, "Type": 112 },
    { "Index": 707, "TimeValue": 76.3461, "Time": "01:16.3461", "Line": 0, "Width": 0, "Type": 112 },
    { "Index": 708, "TimeValue": 78.6538, "Time": "01:18.6538", "Line": 0, "Width": 0, "Type": 112 },
    { "Index": 709, "TimeValue": 78.8461, "Time": "01:18.8461", "Line": 0, "Width": 0, "Type": 112 },
    { "Index": 710, "TimeValue": 79.4230, "Time": "01:19.4230", "Line": 0, "Width": 0, "Type": 112 },
    { "Index": 711, "TimeValue": 79.6153, "Time": "01:19.6153", "Line": 0, "Width": 0, "Type": 112 },
    { "Index": 712, "TimeValue": 79.8076, "Time": "01:19.8076", "Line": 0, "Width": 0, "Type": 112 },
    { "Index": 713, "TimeValue": 83.0769, "Time": "01:23.0769", "Line": 0, "Width": 0, "Type": 112 },
    { "Index": 714, "TimeValue": 86.3461, "Time": "01:26.3461", "Line": 0, "Width": 0, "Type": 112 },
    { "Index": 715, "TimeValue": 86.5384, "Time": "01:26.5384", "Line": 0, "Width": 0, "Type": 112 },
    { "Index": 716, "TimeValue": 84.6153, "Time": "01:24.6153", "Line": 0, "Width": 0, "Type": 112 },
    { "Index": 717, "TimeValue": 84.8076, "Time": "01:24.8076", "Line": 0, "Width": 0, "Type": 112 },
    { "Index": 718, "TimeValue": 85.0000, "Time": "01:25.0000", "Line": 0, "Width": 0, "Type": 112 },
    { "Index": 719, "TimeValue": 85.1923, "Time": "01:25.1923", "Line": 0, "Width": 0, "Type": 112 },
    { "Index": 720, "TimeValue": 85.3846, "Time": "01:25.3846", "Line": 0, "Width": 0, "Type": 112 },
    { "Index": 721, "TimeValue": 85.5769, "Time": "01:25.5769", "Line": 0, "Width": 0, "Type": 112 },
    { "Index": 722, "TimeValue": 85.7692, "Time": "01:25.7692", "Line": 0, "Width": 0, "Type": 112 },
    { "Index": 723, "TimeValue": 85.9615, "Time": "01:25.9615", "Line": 0, "Width": 0, "Type": 112 },
    { "Index": 724, "TimeValue": 88.2692, "Time": "01:28.2692", "Line": 0, "Width": 0, "Type": 112 },
    { "Index": 725, "TimeValue": 88.6538, "Time": "01:28.6538", "Line": 0, "Width": 0, "Type": 112 },
    { "Index": 726, "TimeValue": 93.2692, "Time": "01:33.2692", "Line": 0, "Width": 0, "Type": 112 },
    { "Index": 727, "TimeValue": 96.3461, "Time": "01:36.3461", "Line": 0, "Width": 0, "Type": 112 },
    { "Index": 728, "TimeValue": 96.7307, "Time": "01:36.7307", "Line": 0, "Width": 0, "Type": 112 },
    { "Index": 729, "TimeValue": 97.1153, "Time": "01:37.1153", "Line": 0, "Width": 0, "Type": 112 },
    { "Index": 730, "TimeValue": 99.8076, "Time": "01:39.8076", "Line": 0, "Width": 0, "Type": 112 },
    { "Index": 731, "TimeValue": 99.4230, "Time": "01:39.4230", "Line": 0, "Width": 0, "Type": 112 },
    { "Index": 732, "TimeValue": 99.6153, "Time": "01:39.6153", "Line": 0, "Width": 0, "Type": 112 },
    { "Index": 733, "TimeValue": 99.8076, "Time": "01:39.8076", "Line": 0, "Width": 0, "Type": 112 },
    { "Index": 734, "TimeValue": 107.3076, "Time": "01:47.3076", "Line": 0, "Width": 0, "Type": 112 },
    { "Index": 735, "TimeValue": 108.8461, "Time": "01:48.8461", "Line": 0, "Width": 0, "Type": 112 },
    { "Index": 736, "TimeValue": 110.9615, "Time": "01:50.9615", "Line": 0, "Width": 0, "Type": 112 },
    { "Index": 737, "TimeValue": 111.1538, "Time": "01:51.1538", "Line": 0, "Width": 0, "Type": 112 },
    { "Index": 738, "TimeValue": 110.9615, "Time": "01:50.9615", "Line": 0, "Width": 0, "Type": 112 },
    { "Index": 739, "TimeValue": 111.1538, "Time": "01:51.1538", "Line": 0, "Width": 0, "Type": 112 },
    { "Index": 740, "TimeValue": 113.4615, "Time": "01:53.4615", "Line": 0, "Width": 0, "Type": 112 },
    { "Index": 741, "TimeValue": 115.0000, "Time": "01:55.0000", "Line": 0, "Width": 0, "Type": 112 },
    { "Index": 742, "TimeValue": 117.1153, "Time": "01:57.1153", "Line": 0, "Width": 0, "Type": 112 },
    { "Index": 743, "TimeValue": 117.1153, "Time": "01:57.1153", "Line": 0, "Width": 0, "Type": 112 },
    { "Index": 744, "TimeValue": 122.5000, "Time": "02:02.5000", "Line": 0, "Width": 0, "Type": 112 },
    { "Index": 745, "TimeValue": 122.6923, "Time": "02:02.6923", "Line": 0, "Width": 0, "Type": 112 },
    { "Index": 746, "TimeValue": 122.8846, "Time": "02:02.8846", "Line": 0, "Width": 0, "Type": 112 },
    { "Index": 747, "TimeValue": 123.0769, "Time": "02:03.0769", "Line": 0, "Width": 0, "Type": 112 },
    { "Index": 748, "TimeValue": 123.2692, "Time": "02:03.2692", "Line": 0, "Width": 0, "Type": 112 },
    { "Index": 749, "TimeValue": 123.4615, "Time": "02:03.4615", "Line": 0, "Width": 0, "Type": 112 },
    { "Index": 750, "TimeValue": 123.6538, "Time": "02:03.6538", "Line": 0, "Width": 0, "Type": 112 },
    { "Index": 751, "TimeValue": 123.8461, "Time": "02:03.8461", "Line": 0, "Width": 0, "Type": 112 },
    { "Index": 752, "TimeValue": 124.0384, "Time": "02:04.0384", "Line": 0, "Width": 0, "Type": 112 },
    { "Index": 753, "TimeValue": 124.2307, "Time": "02:04.2307", "Line": 0, "Width": 0, "Type": 112 },
    { "Index": 754, "TimeValue": 124.4230, "Time": "02:04.4230", "Line": 0, "Width": 0, "Type": 112 },
    { "Index": 755, "TimeValue": 124.6153, "Time": "02:04.6153", "Line": 0, "Width": 0, "Type": 112 },
    { "Index": 756, "TimeValue": 124.8076, "Time": "02:04.8076", "Line": 0, "Width": 0, "Type": 112 },
    { "Index": 757, "TimeValue": 125.0000, "Time": "02:05.0000", "Line": 0, "Width": 0, "Type": 112 },
    { "Index": 758, "TimeValue": 125.1923, "Time": "02:05.1923", "Line": 0, "Width": 0, "Type": 112 },
    { "Index": 759, "TimeValue": 125.3846, "Time": "02:05.3846", "Line": 0, "Width": 0, "Type": 112 },
    { "Index": 760, "TimeValue": 125.5769, "Time": "02:05.5769", "Line": 0, "Width": 0, "Type": 112 },
    { "Index": 761, "TimeValue": 125.7692, "Time": "02:05.7692", "Line": 0, "Width": 0, "Type": 112 },
    { "Index": 762, "TimeValue": 125.9615, "Time": "02:05.9615", "Line": 0, "Width": 0, "Type": 112 },
    { "Index": 763, "TimeValue": 126.1538, "Time": "02:06.1538", "Line": 0, "Width": 0, "Type": 112 },
    { "Index": 764, "TimeValue": 126.3461, "Time": "02:06.3461", "Line": 0, "Width": 0, "Type": 112 },
    { "Index": 765, "TimeValue": 122.5000, "Time": "02:02.5000", "Line": 0, "Width": 0, "Type": 112 },
    { "Index": 766, "TimeValue": 122.6923, "Time": "02:02.6923", "Line": 0, "Width": 0, "Type": 112 },
    { "Index": 767, "TimeValue": 122.8846, "Time": "02:02.8846", "Line": 0, "Width": 0, "Type": 112 },
    { "Index": 768, "TimeValue": 123.0769, "Time": "02:03.0769", "Line": 0, "Width": 0, "Type": 112 },
    { "Index": 769, "TimeValue": 123.2692, "Time": "02:03.2692", "Line": 0, "Width": 0, "Type": 112 },
    { "Index": 770, "TimeValue": 123.4615, "Time": "02:03.4615", "Line": 0, "Width": 0, "Type": 112 },
    { "Index": 771, "TimeValue": 123.6538, "Time": "02:03.6538", "Line": 0, "Width": 0, "Type": 112 },
    { "Index": 772, "TimeValue": 123.8461, "Time": "02:03.8461", "Line": 0, "Width": 0, "Type": 112 },
    { "Index": 773, "TimeValue": 124.0384, "Time": "02:04.0384", "Line": 0, "Width": 0, "Type": 112 },
    { "Index": 774, "TimeValue": 124.2307, "Time": "02:04.2307", "Line": 0, "Width": 0, "Type": 112 },
    { "Index": 775, "TimeValue": 124.4230, "Time": "02:04.4230", "Line": 0, "Width": 0, "Type": 112 },
    { "Index": 776, "TimeValue": 124.6153, "Time": "02:04.6153", "Line": 0, "Width": 0, "Type": 112 },
    { "Index": 777, "TimeValue": 124.8076, "Time": "02:04.8076", "Line": 0, "Width": 0, "Type": 112 },
    { "Index": 778, "TimeValue": 125.0000, "Time": "02:05.0000", "Line": 0, "Width": 0, "Type": 112 },
    { "Index": 779, "TimeValue": 125.1923, "Time": "02:05.1923", "Line": 0, "Width": 0, "Type": 112 },
    { "Index": 780, "TimeValue": 125.3846, "Time": "02:05.3846", "Line": 0, "Width": 0, "Type": 112 },
    { "Index": 781, "TimeValue": 125.5769, "Time": "02:05.5769", "Line": 0, "Width": 0, "Type": 112 },
    { "Index": 782, "TimeValue": 125.7692, "Time": "02:05.7692", "Line": 0, "Width": 0, "Type": 112 },
    { "Index": 783, "TimeValue": 125.9615, "Time": "02:05.9615", "Line": 0, "Width": 0, "Type": 112 },
    { "Index": 784, "TimeValue": 126.1538, "Time": "02:06.1538", "Line": 0, "Width": 0, "Type": 112 },
    { "Index": 785, "TimeValue": 126.3461, "Time": "02:06.3461", "Line": 0, "Width": 0, "Type": 112 }
  ],
  "NoteLines": [
    { "Index": 0, "Head": 9, "Tail": 10, "Type": 2, "Notes": [ 622, 623, 624 ] },
    { "Index": 1, "Head": 12, "Tail": 13, "Type": 2, "Notes": [ 625, 626 ] },
    { "Index": 2, "Head": 15, "Tail": 16, "Type": 2, "Notes": [ 627 ] },
    { "Index": 3, "Head": 84, "Tail": 85, "Type": 0, "Notes": [ 628 ] },
    { "Index": 4, "Head": 88, "Tail": 89, "Type": 0, "Notes": [ 629 ] },
    { "Index": 5, "Head": 97, "Tail": 98, "Type": 0, "Notes": [ 630 ] },
    { "Index": 6, "Head": 111, "Tail": 112, "Type": 0, "Notes": [ 631 ] },
    { "Index": 7, "Head": 102, "Tail": 100, "Type": 0, "Notes": [ 632 ] },
    { "Index": 8, "Head": 120, "Tail": 121, "Type": 0, "Notes": [ 633 ] },
    { "Index": 9, "Head": 125, "Tail": 123, "Type": 0, "Notes": [ 634 ] },
    { "Index": 10, "Head": 130, "Tail": 131, "Type": 2, "Notes": [ 635, 636 ] },
    { "Index": 11, "Head": 134, "Tail": 133, "Type": 2, "Notes": [ 637, 638 ] },
    { "Index": 12, "Head": 136, "Tail": 135, "Type": 2, "Notes": [ 639, 640 ] },
    { "Index": 13, "Head": 142, "Tail": 143, "Type": 2, "Notes": [ 641, 642 ] },
    { "Index": 14, "Head": 144, "Tail": 145, "Type": 2, "Notes": [ 643 ] },
    { "Index": 15, "Head": 146, "Tail": 147, "Type": 2, "Notes": [ 644 ] },
    { "Index": 16, "Head": 148, "Tail": 149, "Type": 2, "Notes": [ 645 ] },
    { "Index": 17, "Head": 151, "Tail": 153, "Type": 2, "Notes": [ 646 ] },
    { "Index": 18, "Head": 153, "Tail": 152, "Type": 1, "Notes": [ 647 ] },
    { "Index": 19, "Head": 7, "Tail": 155, "Type": 2, "Notes": [ 648 ] },
    { "Index": 20, "Head": 155, "Tail": 8, "Type": 1, "Notes": [ 649 ] },
    { "Index": 21, "Head": 157, "Tail": 158, "Type": 2, "Notes": [ 650 ] },
    { "Index": 22, "Head": 161, "Tail": 162, "Type": 2, "Notes": [ 651, 652 ] },
    { "Index": 23, "Head": 163, "Tail": 164, "Type": 2, "Notes": [ 653 ] },
    { "Index": 24, "Head": 165, "Tail": 166, "Type": 2, "Notes": [ 654 ] },
    { "Index": 25, "Head": 171, "Tail": 172, "Type": 0, "Notes": [ 655, 656 ] },
    { "Index": 26, "Head": 173, "Tail": 174, "Type": 0 },
    { "Index": 27, "Head": 194, "Tail": 183, "Type": 2, "Notes": [ 657, 658 ] },
    { "Index": 28, "Head": 184, "Tail": 185, "Type": 2, "Notes": [ 659 ] },
    { "Index": 29, "Head": 186, "Tail": 195, "Type": 2, "Notes": [ 660 ] },
    { "Index": 30, "Head": 187, "Tail": 188, "Type": 2, "Notes": [ 661 ] },
    { "Index": 31, "Head": 189, "Tail": 196, "Type": 2, "Notes": [ 662 ] },
    { "Index": 32, "Head": 196, "Tail": 190, "Type": 1, "Notes": [ 663 ] },
    { "Index": 33, "Head": 197, "Tail": 198, "Type": 2, "Notes": [ 664 ] },
    { "Index": 34, "Head": 198, "Tail": 199, "Type": 1, "Notes": [ 665 ] },
    { "Index": 35, "Head": 204, "Tail": 205, "Type": 0, "Notes": [ 206, 207 ] },
    { "Index": 36, "Head": 211, "Tail": 208, "Type": 0, "Notes": [ 209, 210 ] },
    { "Index": 37, "Head": 219, "Tail": 220, "Type": 2, "Notes": [ 666, 667 ] },
    { "Index": 38, "Head": 230, "Tail": 231, "Type": 2, "Notes": [ 668 ] },
    { "Index": 39, "Head": 241, "Tail": 242, "Type": 2, "Notes": [ 669 ] },
    { "Index": 40, "Head": 242, "Tail": 243, "Type": 2, "Notes": [ 670 ] },
    { "Index": 41, "Head": 263, "Tail": 264, "Type": 2, "Notes": [ 671 ] },
    { "Index": 42, "Head": 270, "Tail": 271, "Type": 2, "Notes": [ 672 ] },
    { "Index": 43, "Head": 271, "Tail": 272, "Type": 2, "Notes": [ 673 ] },
    { "Index": 44, "Head": 279, "Tail": 284, "Type": 2, "Notes": [ 674 ] },
    { "Index": 45, "Head": 295, "Tail": 296, "Type": 0, "Notes": [ 675 ] },
    { "Index": 46, "Head": 299, "Tail": 300, "Type": 0, "Notes": [ 676 ] },
    { "Index": 47, "Head": 301, "Tail": 302, "Type": 0, "Notes": [ 677 ] },
    { "Index": 48, "Head": 303, "Tail": 304, "Type": 0, "Notes": [ 678 ] },
    { "Index": 49, "Head": 305, "Tail": 306, "Type": 0, "Notes": [ 679 ] },
    { "Index": 50, "Head": 313, "Tail": 314, "Type": 0, "Notes": [ 680 ] },
    { "Index": 51, "Head": 316, "Tail": 315, "Type": 0, "Notes": [ 681 ] },
    { "Index": 52, "Head": 318, "Tail": 317, "Type": 0, "Notes": [ 682 ] },
    { "Index": 53, "Head": 320, "Tail": 319, "Type": 0, "Notes": [ 683 ] },
    { "Index": 54, "Head": 322, "Tail": 324, "Type": 2, "Notes": [ 684, 685 ] },
    { "Index": 55, "Head": 324, "Tail": 323, "Type": 1, "Notes": [ 686 ] },
    { "Index": 56, "Head": 326, "Tail": 327, "Type": 2, "Notes": [ 687 ] },
    { "Index": 57, "Head": 327, "Tail": 325, "Type": 1, "Notes": [ 688 ] },
    { "Index": 58, "Head": 361, "Tail": 363, "Type": 2, "Notes": [ 689, 690, 691, 692 ] },
    { "Index": 59, "Head": 363, "Tail": 362, "Type": 1, "Notes": [ 693, 694, 695 ] },
    { "Index": 60, "Head": 373, "Tail": 374, "Type": 2, "Notes": [ 696, 697 ] },
    { "Index": 61, "Head": 404, "Tail": 406, "Type": 2, "Notes": [ 698, 699, 700 ] },
    { "Index": 62, "Head": 406, "Tail": 405, "Type": 0, "Notes": [ 701, 702, 703, 704, 705 ] },
    { "Index": 63, "Head": 413, "Tail": 414, "Type": 2, "Notes": [ 706 ] },
    { "Index": 64, "Head": 415, "Tail": 416, "Type": 2, "Notes": [ 707 ] },
    { "Index": 65, "Head": 426, "Tail": 427, "Type": 2, "Notes": [ 708, 709 ] },
    { "Index": 66, "Head": 428, "Tail": 429, "Type": 2, "Notes": [ 710, 711, 712 ] },
    { "Index": 67, "Head": 439, "Tail": 440, "Type": 0, "Notes": [ 713 ] },
    { "Index": 68, "Head": 470, "Tail": 467, "Type": 2, "Notes": [ 714, 715 ] },
    { "Index": 69, "Head": 450, "Tail": 451, "Type": 2, "Notes": [ 716, 717, 718 ] },
    { "Index": 70, "Head": 451, "Tail": 471, "Type": 0, "Notes": [ 719, 720, 721, 722, 723 ] },
    { "Index": 71, "Head": 464, "Tail": 458, "Type": 2, "Notes": [ 724 ] },
    { "Index": 72, "Head": 455, "Tail": 453, "Type": 2, "Notes": [ 725 ] },
    { "Index": 73, "Head": 489, "Tail": 491, "Type": 2, "Notes": [ 726 ] },
    { "Index": 74, "Head": 491, "Tail": 490, "Type": 1 },
    { "Index": 75, "Head": 492, "Tail": 493, "Type": 2, "Notes": [ 727 ] },
    { "Index": 76, "Head": 494, "Tail": 495, "Type": 2, "Notes": [ 728 ] },
    { "Index": 77, "Head": 497, "Tail": 496, "Type": 2, "Notes": [ 729 ] },
    { "Index": 78, "Head": 508, "Tail": 509, "Type": 0, "Notes": [ 730 ] },
    { "Index": 79, "Head": 506, "Tail": 507, "Type": 0, "Notes": [ 731, 732, 733 ] },
    { "Index": 80, "Head": 516, "Tail": 517, "Type": 0, "Notes": [ 518, 519, 520 ] },
    { "Index": 81, "Head": 524, "Tail": 525, "Type": 0, "Notes": [ 521, 523, 522 ] },
    { "Index": 82, "Head": 530, "Tail": 531, "Type": 0, "Notes": [ 734 ] },
    { "Index": 83, "Head": 535, "Tail": 533, "Type": 0, "Notes": [ 735 ] },
    { "Index": 84, "Head": 547, "Tail": 549, "Type": 2, "Notes": [ 736 ] },
    { "Index": 85, "Head": 549, "Tail": 548, "Type": 0, "Notes": [ 737 ] },
    { "Index": 86, "Head": 554, "Tail": 553, "Type": 2, "Notes": [ 738 ] },
    { "Index": 87, "Head": 553, "Tail": 551, "Type": 0, "Notes": [ 739 ] },
    { "Index": 88, "Head": 555, "Tail": 556, "Type": 0, "Notes": [ 557, 558, 559 ] },
    { "Index": 89, "Head": 573, "Tail": 574, "Type": 2, "Notes": [ 740 ] },
    { "Index": 90, "Head": 570, "Tail": 571, "Type": 2, "Notes": [ 741 ] },
    { "Index": 91, "Head": 584, "Tail": 583, "Type": 2, "Notes": [ 742 ] },
    { "Index": 92, "Head": 583, "Tail": 585, "Type": 1 },
    { "Index": 93, "Head": 588, "Tail": 587, "Type": 2, "Notes": [ 743 ] },
    { "Index": 94, "Head": 587, "Tail": 586, "Type": 1 },
    { "Index": 95, "Head": 17, "Tail": 589, "Type": 2, "Notes": [ 744, 745, 746, 747, 748, 749 ] },
    { "Index": 96, "Head": 589, "Tail": 591, "Type": 2, "Notes": [ 750, 751, 752 ] },
    { "Index": 97, "Head": 591, "Tail": 590, "Type": 1, "Notes": [ 753, 754, 755 ] },
    { "Index": 98, "Head": 590, "Tail": 592, "Type": 2, "Notes": [ 756, 757, 758, 759, 760, 761, 762 ] },
    { "Index": 99, "Head": 592, "Tail": 18, "Type": 2, "Notes": [ 763, 764 ] },
    { "Index": 100, "Head": 598, "Tail": 597, "Type": 2, "Notes": [ 765, 766, 767, 768, 769, 770 ] },
    { "Index": 101, "Head": 597, "Tail": 596, "Type": 2, "Notes": [ 771, 772, 773 ] },
    { "Index": 102, "Head": 596, "Tail": 595, "Type": 1, "Notes": [ 774, 775, 776 ] },
    { "Index": 103, "Head": 595, "Tail": 593, "Type": 2, "Notes": [ 777, 778, 779, 780, 781, 782, 783 ] },
    { "Index": 104, "Head": 593, "Tail": 594, "Type": 2, "Notes": [ 784, 785 ] },
    { "Index": 105, "Head": 601, "Tail": 602, "Type": 0, "Notes": [ 603, 604, 605, 606, 607 ] },
    { "Index": 106, "Head": 614, "Tail": 608, "Type": 0, "Notes": [ 609, 610, 611, 612, 613 ] }
  ],
  "SpeedChanges": [
    
  ]
}
